Workbook

Sheet ZH02
B2: Nome | C2: Data de entrada | D2: Senioridade | E2: Remuneração | F2: Valor hora | G2: Notebook | H2: Valor mensal Notebook | I2: Bonus alocado | J2: aumento 1 | K2: aumento 2 | L2: Pagamento Total | M2: Skills
B4: Allan Patrick De Freitas Santana | C4: 44852 | D4: Pleno | E4: 10000 | F4: =E4/168 -> 59.52381 | G4: 14370 | H4: =G4/10 -> 1437 | J4: 2000 | L4: =E4+I4 -> 10000 | M4: React, React native, Node
B5: Raphaela Oliveira | C5: 44830 | D5: Junior | E5: 3000 | F5: =E5/168 -> 17.857143 | G5: 10899 | H5: =G5/10 -> 1089.9 | J5: 2000 | L5: =E5+I5+J5 -> 5000 | M5: Product Designer
B6: Jose Neto | C6: 45019 | D6: Especialista | E6: 18000 | F6: =E6/168 -> 107.14286 | G6: 6259 | H6: =G6/10 -> 625.9 | L6: =E6+I6 -> 18000 | M6: Backend Java
B7: Amanda | C7: 45019 | D7: Junior | E7: 3000 | F7: =E7/168 -> 17.857143 | G7: 10899 | H7: =G7/10 -> 1089.9 | L7: =E7+I7 -> 3000 | M7: Product Designer
B8: Rafael Panhoca | C8: 44927 | D8: Estagiário | E8: 1200 | F8: =E8/168 -> 7.1428571 | L8: =E8+I8 -> 1200 | M8: Estagiário
B9: Gustavo Rodrigues | C9: 45018 | D9: Pleno | E9: 8000 | F9: =E9/168 -> 47.619048 | G9: 15200 | H9: =G9/10 -> 1520 | I9: 1500 | L9: =E9+I9 -> 9500 | M9: ReactJS, React Native, Node
B10: Matheus Alcatrao | C10: 45019 | D10: Pleno | E10: 8000 | F10: =E10/168 -> 47.619048 | G10: 15200 | H10: =G10/10 -> 1520 | I10: 1500 | L10: =E10+I10 -> 9500 | M10: ReactJS, React Native, Node
B11: Gabriel Paiva | C11: 45019 | D11: Pleno | E11: 9000 | F11: =E11/168 -> 53.571429 | G11: 15200 | H11: =G11/10 -> 1520 | L11: =E11+I11 -> 9000 | M11: ReactJS, React Native, Node
B12: Gabriela Briglia Coni | C12: 45019 | D12: Junior | E12: 6500 | F12: =E12/168 -> 38.690476 | G12: 6259 | H12: =G12/10 -> 625.9 | L12: =E12+I12 -> 6500 | M12: Produto e Agilidade
B13: Mateus Chaves | C13: 45068 | D13: Senior | E13: 9000 | F13: =E13/168 -> 53.571429 | G13: 15500 | H13: =G13/10 -> 1550 | I13: 1000 | L13: =E13+I13 -> 10000 | M13: ReactJS, React Native, Node
B14: Arthur | C14: 45007 | D14: Pleno | E14: 13000 | F14: =E14/168 -> 77.380952 | G14: 5359 | H14: =G14/10 -> 535.9 | L14: =E14+I14 -> 13000 | M14: Backend Java
B15: Fernando | C15: 45070 | D15: Estagiário | E15: 1200 | F15: =E15/168 -> 7.1428571 | L15: =E15+I15 -> 1200 | M15: React, React Native
B16: Alice Almeida | C16: 45078 | D16: Pleno | E16: 8850 | F16: =E16/168 -> 52.678571 | G16: 3514 | H16: =G16/10 -> 351.4 | L16: =E16+I16 -> 8850 | M16: Pessoas
B17: Nathan Santos | C17: 45047 | D17: Senior | E17: 15000 | F17: =E17/168 -> 89.285714 | H17: =G17/10 -> 0 | L17: =E17+I17 -> 15000 | M17: Produto e Gestão
B18: Aline Santos | C18: 45096 | D18: Senior | E18: 16500 | F18: =E18/168 -> 98.214286 | G18: 6460 | H18: =G18/10 -> 646 | L18: =E18+I18 -> 16500 | M18: Backend Java
B19: Renata Dias | C19: 45110 | D19: Senior | E19: 18000 | F19: =E19/168 -> 107.14286 | G19: 3389 | H19: =G19/10 -> 338.9 | L19: =E19+I19 -> 18000 | M19: Produto e Gestão
B20: Ericsson Teixeira | C20: 45110 | D20: Pleno | E20: 9000 | F20: =E20/168 -> 53.571429 | G20: 15200 | H20: =G20/10 -> 1520 | I20: 1500 | L20: =E20+I20 -> 10500
B21: Caique Oliveira | C21: 45110 | D21: Senior | E21: 14000 | F21: =E21/168 -> 83.333333 | G21: 14959 | H21: =G21/10 -> 1495.9 | L21: =E21+I21 -> 14000
B22: Jonatham Gomes | C22: 45103 | D22: Senior | E22: 12000 | F22: =E22/168 -> 71.428571 | G22: 6600 | H22: =G22/10 -> 660 | L22: =E22+I22 -> 12000
B23: Alexsandro Ramos | C23: 45126 | D23: Senior | E23: 12000 | F23: =E23/168 -> 71.428571 | G23: 15500 | H23: =G23/10 -> 1550 | L23: =E23+I23 -> 12000
B24: TBD - Sócio | F24: 0 | G24: 0 | H24: 0 | N24: 320
B25: TBD - Gestão | F25: 148.80952 | G25: 7500 | H25: =G25/10 -> 750 | N25: 320
B26: TBD - Product Manager Senior | E26: 18000 | F26: 119.04762 | G26: 7500 | H26: =G26/10 -> 750 | N26: 260
B27: TBD - Product Manager Pleno | E27: 13000 | F27: 71.428571 | G27: 7500 | H27: =G27/10 -> 750 | N27: 200
B28: TBD - Product Designer Senior | E28: 15000 | F28: 71.428571 | G28: 10899 | H28: =G28/10 -> 1089.9 | N28: 200
B29: TBD - Product Designer Pleno | E29: 10000 | F29: 50.595238 | G29: 10899 | H29: =G29/10 -> 1089.9 | N29: 170
B30: TBD - Product Designer Junior | E30: 5000 | F30: 38.690476 | G30: 10899 | H30: =G30/10 -> 1089.9 | N30: 130
B31: TBD - QA Senior | E31: 15000 | F31: 71.428571 | G31: 14370 | H31: =G31/10 -> 1437 | N31: 170
B32: TBD - QA Pleno | E32: 10000 | F32: 50.595238 | G32: 14370 | H32: =G32/10 -> 1437 | N32: 150
B33: TBD - QA Junior | E33: 5000 | F33: 38.690476 | G33: 14370 | H33: =G33/10 -> 1437 | N33: 130
B34: TBD - DevOps | E34: 18000 | F34: 71.428571 | G34: 14370 | H34: =G34/10 -> 1437 | N34: 260
B35: TBD - Dev Junior | E35: 5000 | F35: 38.690476 | G35: 14370 | H35: =G35/10 -> 1437 | N35: 130
B36: TBD - Dev Pleno | E36: 10000 | F36: 50.595238 | G36: 14370 | H36: =G36/10 -> 1437 | N36: 160
B37: TBD - Dev Senior | E37: 15000 | F37: 71.428571 | G37: 14370 | H37: =G37/10 -> 1437 | N37: 180
... B39: TBD - SME | E39: 23000 | F39: 148.80952 | G39: 7500 | H39: =G39/10 -> 750 | N39: 320

Sheet CUPONI
A1: PREMISSAS | B1: 44927 | C1: 44958 | D1: 44986 | E1: 45017 | F1: 45047 | G1: 45078 | H1: 45108 | I1: 45139 | J1: 45170 | K1: 45200 | L1: 45231 | M1: 45261 | N1: 45292 | O1: TOTAL
A2: Cuponi - Fatura | B2: 10820 | C2: 7140 | D2: 3480 | E2: 5160 | F2: =4800+6500 -> 11300 | G2: =4800+6500 -> 11300 | H2: =4800+6500 -> 11300 | I2: 4800 | J2: 4800 | K2: 4800 | L2: 4800 | M2: 4800 | N2: 0 | O2: =SUM(B2:N2) -> 84500
A3: Cuponi - Receita liquida | B3: =B2*(1-B5) -> 10170.8 | C3: =C2*(1-C5) -> 6711.6 | D3: =D2*(1-D5) -> 3271.2 | E3: =E2*(1-E5) -> 4850.4 | F3: =F2*(1-F5) -> 10622 | G3: =G2*(1-G5) -> 10622 | H3: =H2*(1-H5) -> 10622 | I3: =I2*(1-I5) -> 4512 | ... M3: =M2*(1-M5) -> 4512 | N3: 0 | O3: =SUM(B3:M3) -> 79430
A5: IMPOSTOS | B5: 0.06 | C5: 0.06 | D5: 0.06 | E5: 0.06 | F5: 0.06 | G5: 0.06 | H5: 0.06 | I5: 0.06 | J5: 0.06 | K5: 0.06 | L5: 0.06 | M5: 0.06 | N5: 0.06
A7: CMV (Custo da Mercadoria Vendida) | B7: 44927 | C7: 44958 | D7: 44986 | E7: 45017 | F7: 45047 | G7: 45078 | H7: 45108 | I7: 45139 | J7: 45170 | K7: 45200 | L7: 45231 | M7: 45261 | N7: 45292 | O7: TOTAL
A8: =A3 -> Cuponi - Receita liquida | B8: =B14 -> -13000 | C8: =C14 -> -13220 | D8: =D14 -> -11036 | E8: =E14 -> -1184 | F8: =F14 -> -1560 | G8: =G14 -> -9300 | H8: =H14 -> -9300 | I8: =I14 -> -9300 | ... N8: =N14 -> -2800 | O8: =SUM(D8:N8) -> -55680
A10: LUCRO (CCI) | B10: 44927 | C10: 44958 | D10: 44986 | E10: 45017 | F10: 45047 | G10: 45078 | H10: 45108 | I10: 45139 | J10: 45170 | K10: 45200 | L10: 45231 | M10: 45261 | N10: 45292 | O10: TOTAL
A11: =A3 -> Cuponi - Receita liquida | B11: =B3+B8 -> -2829.2 | C11: =C3+C8 -> -6508.4 | D11: =D3+D8 -> -7764.8 | E11: =E3+E8 -> 3666.4 | F11: =F3+F8 -> 9062 | G11: =G3+G8 -> 1322 | H11: =H3+H8 -> 1322 | I11: =I3+I8 -> -4788 | ... N11: =N3+N8 -> -2800 | O11: =SUM(D11:N11) -> 6867.6
B12: =B11/B3 -> -0.27816888 | C12: =C11/C3 -> -0.96972406 | D12: =D11/D3 -> -2.3736855 | E12: =E11/E3 -> 0.75589642 | F12: =F11/F3 -> 0.853135 | G12: =G11/G3 -> 0.12445867 | H12: =H11/H3 -> 0.12445867 | I12: =I11/I3 -> -1.0611702 | ... N12: =N11/N3 -> #DIV/0!
A14: =A8 -> Cuponi - Receita liquida | B14: =B15+B19+B21 -> -13000 | C14: =C15+C19+C21 -> -13220 | D14: =D15+D19+D21 -> -11036 | E14: =E15+E19+E21 -> -1184 | F14: =F15+F19+F21 -> -1560 | G14: =G15+G19+G21 -> -9300 | H14: =H15+H19+H21 -> -9300 | I14: =I15+I19+I21 -> -9300 | ... O14: =O15+O19+O21 -> -55680
A15: Time | B15: =SUM(B16:B18) -> -10000 | C15: =SUM(C16:C18) -> -10220 | D15: =SUM(D16:D18) -> -11036 | E15: =SUM(E16:E18) -> -1184 | F15: =SUM(F16:F18) -> -1560 | G15: =SUM(G16:G18) -> -9300 | H15: =SUM(H16:H18) -> -9300 | I15: =SUM(I16:I18) -> -9300 | ... N15: =SUM(N16:N18) -> -2800 | O15: =SUM(D15:N15) -> -55680
A16: Allan Patrick De Freitas Santana | B16: =-VLOOKUP($A$16,'ZH02'!$B:$N,4,0) -> -10000 | C16: =-VLOOKUP($A$16,'ZH02'!$B:$N,4,0) -> -10000 | D16: =-VLOOKUP($A$16,'ZH02'!$B:$N,4,0) -> -10000 | F16: -780 | G16: =-65*20 -> -1300 | H16: =-65*20 -> -1300 | I16: =-65*20 -> -1300 | J16: =-65*20 -> -1300 | K16: =-65*20 -> -1300 | L16: =-65*20 -> -1300 | M16: =-65*20 -> -1300 | N16: =-65*20 -> -1300
A17: Gabriela Briglia Coni | G17: =-VLOOKUP($A$17,'ZH02'!$B:$N,4,0) -> -6500 | H17: =-VLOOKUP($A$17,'ZH02'!$B:$N,4,0) -> -6500 | I17: =-VLOOKUP($A$17,'ZH02'!$B:$N,4,0) -> -6500
A18: Arthur | C18: -220 | D18: -1036 | E18: -1184 | F18: -780 | G18: =-75*20 -> -1500 | H18: =-75*20 -> -1500 | I18: =-75*20 -> -1500 | J18: =-75*20 -> -1500 | K18: =-75*20 -> -1500 | L18: =-75*20 -> -1500 | M18: =-75*20 -> -1500 | N18: =-75*20 -> -1500
A19: Design | B19: -3000 | C19: -3000 | D19: =SUM(D20) -> 0 | E19: =SUM(E20) -> 0 | F19: =SUM(F20) -> 0 | G19: =SUM(G20) -> 0 | H19: =SUM(H20) -> 0 | I19: =SUM(I20) -> 0 | J19: =SUM(J20) -> 0 | K19: =SUM(K20) -> 0 | ... N19: =SUM(N20) -> 0 | O19: =SUM(D19:N19) -> 0
A20: Raphaela Oliveira | B20: =-VLOOKUP($A$20,'ZH02'!$B:$N,4,0) -> -3000 | C20: =-VLOOKUP($A$20,'ZH02'!$B:$N,4,0) -> -3000 | O20: =SUM(D20:N20) -> 0
A21: Outros custos gerais | B21: =SUM(B22:B23) -> 0 | C21: =SUM(C22:C23) -> 0 | D21: =SUM(D22:D23) -> 0 | E21: =SUM(E22:E23) -> 0 | F21: =SUM(F22:F23) -> 0 | G21: =SUM(G22:G23) -> 0 | H21: =SUM(H22:H23) -> 0 | I21: =SUM(I22:I23) -> 0 | ... N21: =SUM(N22:N23) -> 0 | O21: =SUM(D21:N21) -> 0
E28: =42.5*120 -> 5100

Sheet MANI
A1: PREMISSAS | B1: 44927 | C1: 44958 | D1: 44986 | E1: 45017 | F1: 45047 | G1: 45078 | H1: 45108 | I1: 45139 | J1: 45170 | K1: 45200 | L1: 45231 | M1: 45261 | N1: 45292 | O1: TOTAL
A2: FATURAMENTO | B2: =SUM(B3:B5) -> 0 | C2: =SUM(C3:C5) -> 39776 | D2: =SUM(D3:D5) -> 49606.4 | E2: =SUM(E3:E5) -> 76000 | F2: =SUM(F3:F5) -> 89030.4 | G2: =SUM(G3:G5) -> 55104 | H2: =SUM(H3:H5) -> 34944 | I2: =SUM(I3:I5) -> 34944 | ... N2: =SUM(N3:N5) -> 0 | O2: =SUM(B2:M2) -> 394188.8
A3: Mani - Produto & Design | C3: 39776 | D3: 49606.4 | E3: 40979.2 | F3: 36608 | G3: 34944 | H3: 14784 | I3: 14784 | J3: 14784 | O3: =SUM(B3:M3) -> 246265.6
A4: Mani - Desenvolvedores | E4: 35020.8 | F4: 40550.4 | G4: 20160 | H4: 20160 | I4: 20160 | O4: =SUM(B4:M4) -> 136051.2
A5: Mani - Lps | F5: 11872 | O5: =SUM(B5:M5) -> 11872
A6: RECEITA LÍQUIDA | B6: =SUM(B3:B5)*(1-B8) -> 0 | C6: =SUM(C3:C5)*(1-C8) -> 37389.44 | D6: =SUM(D3:D5)*(1-D8) -> 46630.016 | E6: =SUM(E3:E5)*(1-E8) -> 69920 | F6: =SUM(F3:F5)*(1-F8) -> 81907.968 | G6: =SUM(G3:G5)*(1-G8) -> 50695.68 | H6: =SUM(H3:H5)*(1-H8) -> 32148.48 | I6: =SUM(I3:I5)*(1-I8) -> 32148.48 | ... M6: =SUM(M3:M5)*(1-M8) -> 0 | O6: =SUM(B6:M6) -> 364441.34
A8: IMPOSTOS | B8: 0.06 | C8: 0.06 | D8: 0.06 | E8: 0.08 | F8: 0.08 | G8: 0.08 | H8: 0.08 | I8: 0.08 | J8: 0.08 | K8: 0.1 | L8: 0.1 | M8: 0.18 | N8: 0.18
A10: CMV (Custo da Mercadoria Vendida) | B10: 44927 | C10: 44958 | D10: 44986 | E10: 45017 | F10: 45047 | G10: 45078 | H10: 45108 | I10: 45139 | J10: 45170 | K10: 45200 | L10: 45231 | M10: 45261 | N10: 45292 | O10: TOTAL
A11: Reune | B11: =B17 -> 0 | D11: =D17 -> -3000 | E11: =E17 -> -3000 | F11: =F17 -> -22000 | G11: =G17 -> -22000 | H11: =H17 -> -7500 | I11: =I17 -> 0 | J11: =J17 -> 0 | K11: =K17 -> 0 | ... N11: =N17 -> 0 | O11: =SUM(D11:M11) -> -57500 | T11: TBD - Sócio | U11: 176 | W11: =V11*U11 -> 0
T12: Raphaela Oliveira | U12: 120 | W12: =V12*U12 -> 0
A13: LUCRO (CCI) | B13: 44927 | C13: 44958 | D13: 44986 | E13: 45017 | F13: 45047 | G13: 45078 | H13: 45108 | I13: 45139 | J13: 45170 | K13: 45200 | L13: 45231 | M13: 45261 | N13: 45292 | O13: TOTAL | T13: Gustavo Rodrigues | U13: 120 | V13: 168 | W13: =V13*U13 -> 20160
A14: Reune | B14: =B6+B11 -> 0 | C14: =C6+C11 -> 37389.44 | D14: =D6+D11 -> 43630.016 | E14: =E6+E11 -> 66920 | F14: =F6+F11 -> 59907.968 | G14: =G6+G11 -> 28695.68 | H14: =H6+H11 -> 24648.48 | I14: =I6+I11 -> 32148.48 | ... N14: =N6+N11 -> 0 | O14: =SUM(D14:M14) -> 269551.9 | T14: Vinicius | U14: 110.4 | V14: 168 | W14: =V14*U14 -> 18547.2
B15: =B14/B6 -> #DIV/0! | C15: =C14/C6 -> 1 | D15: =D14/D6 -> 0.93566376 | E15: =E14/E6 -> 0.95709382 | F15: =F14/F6 -> 0.73140586 | G15: =G14/G6 -> 0.56603797 | H15: =H14/H6 -> 0.76670748 | I15: =I14/I6 -> 1 | ... O15: =O14/O6 -> 0.73963042 | V15: 168 | W15: =V15*U15 -> 0
W16: =SUM(W11:W15) -> 38707.2
A17: =A11 -> Reune | B17: =B18+B21+B23 -> 0 | C17: =C18+C21+C23 -> 0 | D17: =D18+D21+D23 -> -3000 | E17: =E18+E21+E23 -> -3000 | F17: =F18+F21+F23 -> -22000 | G17: =G18+G21+G23 -> -22000 | H17: =H18+H21+H23 -> -7500 | I17: =I18+I21+I23 -> 0 | ... O17: =O18+O21+O23 -> -57500
A18: Desenvolvimento | B18: =SUM(B19:B20) -> 0 | C18: =SUM(C19:C20) -> 0 | D18: =SUM(D19:D20) -> 0 | E18: =SUM(E19:E20) -> 0 | F18: =SUM(F19:F20) -> -19000 | G18: =SUM(G19:G20) -> -19000 | H18: =SUM(H19:H20) -> -4500 | I18: =SUM(I19:I20) -> 0 | ... N18: =SUM(N19:N20) -> 0 | O18: =SUM(D18:M18) -> -42500
A19: Allan Patrick De Freitas Santana | F19: =-VLOOKUP($A$19,'ZH02'!$B:$N,4,0) -> -10000 | G19: =-VLOOKUP($A$19,'ZH02'!$B:$N,4,0) -> -10000
A20: Gabriel Paiva | F20: =-VLOOKUP($A$20,'ZH02'!$B:$N,4,0) -> -9000 | G20: =-VLOOKUP($A$20,'ZH02'!$B:$N,4,0) -> -9000 | H20: =(-VLOOKUP($A$20,'ZH02'!$B:$N,4,0))/2 -> -4500
A21: Design | B21: =SUM(B22) -> 0 | C21: =SUM(C22) -> 0 | D21: =SUM(D22) -> -3000 | E21: =SUM(E22) -> -3000 | F21: =SUM(F22) -> -3000 | G21: =SUM(G22) -> -3000 | H21: =SUM(H22) -> -3000 | I21: =SUM(I22) -> 0 | ... N21: =SUM(N22) -> 0 | O21: =SUM(D21:M21) -> -15000
A22: Raphaela Oliveira | D22: -3000 | E22: -3000 | F22: -3000 | G22: =-VLOOKUP($A$22,'ZH02'!$B:$N,4,0) -> -3000 | H22: =-VLOOKUP($A$22,'ZH02'!$B:$N,4,0) -> -3000
A23: Outros custos gerais | B23: =SUM(B24:B25) -> 0 | C23: =SUM(C24:C25) -> 0 | D23: =SUM(D24:D25) -> 0 | E23: =SUM(E24:E25) -> 0 | F23: =SUM(F24:F25) -> 0 | G23: =SUM(G24:G25) -> 0 | H23: =SUM(H24:H25) -> 0 | I23: =SUM(I24:I25) -> 0 | ... N23: =SUM(N24:N25) -> 0 | O23: =SUM(D23:M23) -> 0
A24: Viagens

Sheet ANBIMA - Saida de Dados
A1: PREMISSAS | B1: 44927 | C1: 44958 | D1: 44986 | E1: 45017 | F1: 45047 | G1: 45078 | H1: 45108 | I1: 45139 | J1: 45170 | K1: 45200 | L1: 45231 | M1: 45261 | N1: 45292 | O1: TOTAL
A2: Reune - Fatura | G2: 49800 | H2: 254960 | I2: 368000 | J2: 356000 | K2: 420000 | L2: 380000 | M2: 400000 | O2: =SUM(D2:M2) -> 2228760
A3: Reune- Receita liquida | B3: =B2*(1-B5) -> 0 | C3: =C2*(1-C5) -> 0 | D3: =D2*(1-D5) -> 0 | E3: =E2*(1-E5) -> 0 | F3: =F2*(1-F5) -> 0 | G3: =G2*(1-G5) -> 44820 | H3: =H2*(1-H5) -> 229464 | I3: =I2*(1-I5) -> 301760 | ... M3: =M2*(1-M5) -> 328000 | O3: =SUM(D3:M3) -> 1851964
A5: IMPOSTOS | B5: 0.06 | C5: 0.06 | D5: 0.06 | E5: 0.06 | F5: 0.06 | G5: 0.1 | H5: 0.1 | I5: 0.18 | J5: 0.18 | K5: 0.18 | L5: 0.18 | M5: 0.18
A7: CMV (Custo da Mercadoria Vendida) | B7: 44927 | C7: 44958 | D7: 44986 | E7: 45017 | F7: 45047 | G7: 45078 | H7: 45108 | I7: 45139 | J7: 45170 | K7: 45200 | L7: 45231 | M7: 45261 | N7: 45292 | O7: TOTAL
A8: Reune | B8: =B14 -> 0 | C8: =C14 -> 0 | D8: =D14 -> 0 | E8: =E14 -> 0 | F8: =F14 -> 0 | G8: =G14 -> 0 | H8: =H14 -> -20928.576 | I8: =I14 -> -124500 | ... N8: =N14 -> -169500 | O8: =SUM(D8:M8) -> -784142.86 | T8: TBD - Product Manager Senior | U8: 260 | V8: 40 | W8: =V8*U8 -> 10400
T9: TBD - Product Designer Junior | U9: 104 | V9: 40 | W9: =V9*U9 -> 4160
A10: LUCRO (CCI) | B10: 44927 | C10: 44958 | D10: 44986 | E10: 45017 | F10: 45047 | G10: 45078 | H10: 45108 | I10: 45139 | J10: 45170 | K10: 45200 | L10: 45231 | M10: 45261 | N10: 45292 | O10: TOTAL | T10: TBD - Especialista | U10: 240 | V10: 40 | W10: =V10*U10 -> 9600
A11: Reune | B11: =B3+B8 -> 0 | C11: =C3+C8 -> 0 | D11: =D3+D8 -> 0 | E11: =E3+E8 -> 0 | F11: =F3+F8 -> 0 | G11: =G3+G8 -> 44820 | H11: =H3+H8 -> 208535.42 | I11: =I3+I8 -> 177260 | ... N11: =N3+N8 -> -169500 | O11: =SUM(D11:N11) -> 898321.14 | T11: TBD - Dev Pleno | U11: 160 | W11: =V11*U11 -> 0
B12: =B11/B3 -> #DIV/0! | C12: =C11/C3 -> #DIV/0! | D12: =D11/D3 -> #DIV/0! | E12: =E11/E3 -> #DIV/0! | F12: =F11/F3 -> #DIV/0! | G12: =G11/G3 -> 1 | H12: =H11/H3 -> 0.90879364 | I12: =I11/I3 -> 0.58742047 | ... O12: =O11/O3 -> 0.48506404 | T12: TBD - Dev Senior | U12: 180 | W12: =V12*U12 -> 0
W13: =SUM(W8:W12) -> 24160
A14: =A8 -> Reune | B14: =B15+B30 -> 0 | C14: =C15+C30 -> 0 | D14: =D15+D30 -> 0 | E14: =E15+E30 -> 0 | F14: =F15+F30 -> 0 | G14: =G15+G30 -> 0 | H14: =H15+H30 -> -20928.576 | I14: =I15+I30 -> -124500 | ... O14: =O15+O30 -> -784142.86
A15: Desenvolvimento | B15: =SUM(B16:B29) -> 0 | C15: =SUM(C16:C29) -> 0 | D15: =SUM(D16:D29) -> 0 | E15: =SUM(E16:E29) -> 0 | F15: =SUM(F16:F29) -> 0 | G15: =SUM(G16:G29) -> 0 | H15: =SUM(H16:H29) -> -20928.576 | I15: =SUM(I16:I29) -> -124500 | ... N15: =SUM(N16:N29) -> -169500 | O15: =SUM(D15:M15) -> -784142.86
A16: TBD - Sócio | H16: =-VLOOKUP($A16,'ZH02'!$B:$N,4,0) -> 0 | I16: =-VLOOKUP($A16,'ZH02'!$B:$N,4,0) -> 0 | J16: =-VLOOKUP($A16,'ZH02'!$B:$N,4,0) -> 0 | K16: =-VLOOKUP($A16,'ZH02'!$B:$N,4,0) -> 0 | L16: =-VLOOKUP($A16,'ZH02'!$B:$N,4,0) -> 0 | M16: =-VLOOKUP($A16,'ZH02'!$B:$N,4,0) -> 0 | N16: =-VLOOKUP($A16,'ZH02'!$B:$N,4,0) -> 0 | S16: Anbima - Saída de dados
A17: Renata Dias | I17: =-VLOOKUP($A17,'ZH02'!$B:$N,4,0) -> -18000 | J17: =-VLOOKUP($A17,'ZH02'!$B:$N,4,0) -> -18000 | K17: =-VLOOKUP($A17,'ZH02'!$B:$N,4,0) -> -18000 | L17: =-VLOOKUP($A17,'ZH02'!$B:$N,4,0) -> -18000 | M17: =-VLOOKUP($A17,'ZH02'!$B:$N,4,0) -> -18000 | N17: =-VLOOKUP($A17,'ZH02'!$B:$N,4,0) -> -18000 | Q17: 13000 | S17: Mês | T17: Valor | U17: Horas
A18: Alexsandro Ramos | H18: -5714.29 | I18: =-VLOOKUP($A18,'ZH02'!$B:$N,4,0) -> -12000 | J18: =-VLOOKUP($A18,'ZH02'!$B:$N,4,0) -> -12000 | K18: =-VLOOKUP($A18,'ZH02'!$B:$N,4,0) -> -12000 | L18: =-VLOOKUP($A18,'ZH02'!$B:$N,4,0) -> -12000 | M18: =-VLOOKUP($A18,'ZH02'!$B:$N,4,0) -> -12000 | N18: =-VLOOKUP($A18,'ZH02'!$B:$N,4,0) -> -12000 | Q18: =Q17/21 -> 619.04762 | S18: 45017 | T18: - | U18: -
A19: TBD - QA Pleno | J19: =-VLOOKUP($A19,'ZH02'!$B:$N,4,0) -> -10000 | K19: =-VLOOKUP($A19,'ZH02'!$B:$N,4,0) -> -10000 | L19: =-VLOOKUP($A19,'ZH02'!$B:$N,4,0) -> -10000 | M19: =-VLOOKUP($A19,'ZH02'!$B:$N,4,0) -> -10000 | N19: =-VLOOKUP($A19,'ZH02'!$B:$N,4,0) -> -10000 | Q19: =Q18*9 -> 5571.4286 | S19: 45047 | T19: - | U19: -
A20: Caique Oliveira | I20: =-VLOOKUP($A20,'ZH02'!$B:$N,4,0) -> -14000 | J20: =-VLOOKUP($A20,'ZH02'!$B:$N,4,0) -> -14000 | K20: =-VLOOKUP($A20,'ZH02'!$B:$N,4,0) -> -14000 | L20: =-VLOOKUP($A20,'ZH02'!$B:$N,4,0) -> -14000 | M20: =-VLOOKUP($A20,'ZH02'!$B:$N,4,0) -> -14000 | N20: =-VLOOKUP($A20,'ZH02'!$B:$N,4,0) -> -14000 | S20: 45078 | T20: 49800 | U20: ='[1]Anbima - Junho - 23'!R60 -> #REF!
A21: Gabriel Paiva | H21: =(-VLOOKUP($A21,'ZH02'!$B:$N,4,0))/2 -> -4500 | I21: =-VLOOKUP($A21,'ZH02'!$B:$N,4,0) -> -9000 | J21: =-VLOOKUP($A21,'ZH02'!$B:$N,4,0) -> -9000 | K21: =-VLOOKUP($A21,'ZH02'!$B:$N,4,0) -> -9000 | L21: =-VLOOKUP($A21,'ZH02'!$B:$N,4,0) -> -9000 | M21: =-VLOOKUP($A21,'ZH02'!$B:$N,4,0) -> -9000 | N21: =-VLOOKUP($A21,'ZH02'!$B:$N,4,0) -> -9000 | S21: 45108 | T21: 254960 | U21: ='[1]Anbima - Julho - 23'!R67 -> #REF!
A22: TBD - Dev Pleno | I22: =(-VLOOKUP($A22,'ZH02'!$B:$N,4,0))/2 -> -5000 | J22: =-VLOOKUP($A22,'ZH02'!$B:$N,4,0) -> -10000 | K22: =-VLOOKUP($A22,'ZH02'!$B:$N,4,0) -> -10000 | L22: =-VLOOKUP($A22,'ZH02'!$B:$N,4,0) -> -10000 | M22: =-VLOOKUP($A22,'ZH02'!$B:$N,4,0) -> -10000 | N22: =-VLOOKUP($A22,'ZH02'!$B:$N,4,0) -> -10000 | S22: 45139 | T22: 368000 | U22: ='[1]Anbima - Agosto - 23 '!R65 -> #REF!
A23: Allan Patrick De Freitas Santana | K23: -5142.8571 | L23: -12000 | M23: -12000 | N23: -12000 | S23: 45170 | T23: 356000 | U23: ='[1]Anbima - Setembro - 23'!R65 -> #REF!
A24: Aline Santos | H24: -7857.1429 | I24: =-VLOOKUP($A24,'ZH02'!$B:$N,4,0) -> -16500 | J24: =-VLOOKUP($A24,'ZH02'!$B:$N,4,0) -> -16500 | K24: =-VLOOKUP($A24,'ZH02'!$B:$N,4,0) -> -16500 | L24: =-VLOOKUP($A24,'ZH02'!$B:$N,4,0) -> -16500 | M24: =-VLOOKUP($A24,'ZH02'!$B:$N,4,0) -> -16500 | N24: =-VLOOKUP($A24,'ZH02'!$B:$N,4,0) -> -16500 | S24: 45200 | T24: 420000 | U24: ='[1]Anbima - Outubro - 23'!R53 -> #REF!
A25: Jonatham Gomes | H25: -2857.1429 | I25: =-VLOOKUP($A25,'ZH02'!$B:$N,4,0) -> -12000 | J25: =-VLOOKUP($A25,'ZH02'!$B:$N,4,0) -> -12000 | K25: =-VLOOKUP($A25,'ZH02'!$B:$N,4,0) -> -12000 | L25: =-VLOOKUP($A25,'ZH02'!$B:$N,4,0) -> -12000 | M25: =-VLOOKUP($A25,'ZH02'!$B:$N,4,0) -> -12000 | N25: =-VLOOKUP($A25,'ZH02'!$B:$N,4,0) -> -12000 | S25: 45231 | T25: 380000 | U25: ='[1]Anbima - Novembro - 23'!R53 -> #REF!
A26: TBD - Dev Pleno | I26: =(-VLOOKUP($A26,'ZH02'!$B:$N,4,0))/2 -> -5000 | J26: =-VLOOKUP($A26,'ZH02'!$B:$N,4,0) -> -10000 | K26: =-VLOOKUP($A26,'ZH02'!$B:$N,4,0) -> -10000 | L26: =-VLOOKUP($A26,'ZH02'!$B:$N,4,0) -> -10000 | M26: =-VLOOKUP($A26,'ZH02'!$B:$N,4,0) -> -10000 | N26: =-VLOOKUP($A26,'ZH02'!$B:$N,4,0) -> -10000 | S26: 45261 | T26: 400000 | U26: ='[1]Anbima - Dezembro - 23'!R54 -> #REF!
A27: Arthur | K27: -5571.4286 | L27: =-VLOOKUP($A27,'ZH02'!$B:$N,4,0) -> -13000 | M27: =-VLOOKUP($A27,'ZH02'!$B:$N,4,0) -> -13000 | N27: =-VLOOKUP($A27,'ZH02'!$B:$N,4,0) -> -13000 | S27: Total | T27: =SUM(T20:T26) -> 2228760 | U27: =SUM(U18:U26) -> #REF!
A28: Jose Neto | I28: =-VLOOKUP($A28,'ZH02'!$B:$N,4,0) -> -18000 | J28: =-VLOOKUP($A28,'ZH02'!$B:$N,4,0) -> -18000 | K28: =-VLOOKUP($A28,'ZH02'!$B:$N,4,0) -> -18000 | L28: =-VLOOKUP($A28,'ZH02'!$B:$N,4,0) -> -18000 | M28: =-VLOOKUP($A28,'ZH02'!$B:$N,4,0) -> -18000 | N28: =-VLOOKUP($A28,'ZH02'!$B:$N,4,0) -> -18000
A29: TBD - Dev Senior | I29: =-VLOOKUP($A29,'ZH02'!$B:$N,4,0) -> -15000 | J29: =-VLOOKUP($A29,'ZH02'!$B:$N,4,0) -> -15000 | K29: =-VLOOKUP($A29,'ZH02'!$B:$N,4,0) -> -15000 | L29: =-VLOOKUP($A29,'ZH02'!$B:$N,4,0) -> -15000 | M29: =-VLOOKUP($A29,'ZH02'!$B:$N,4,0) -> -15000 | N29: =-VLOOKUP($A29,'ZH02'!$B:$N,4,0) -> -15000
A30: Outros custos gerais | B30: =SUM(B31:B32) -> 0 | C30: =SUM(C31:C32) -> 0 | D30: =SUM(D31:D32) -> 0 | E30: =SUM(E31:E32) -> 0 | F30: =SUM(F31:F32) -> 0 | G30: =SUM(G31:G32) -> 0 | H30: =SUM(H31:H32) -> 0 | I30: =SUM(I31:I32) -> 0 | ... N30: =SUM(N31:N32) -> 0 | O30: =SUM(D30:M30) -> 0
A31: Viagens

Sheet ANBIMA - REUNE
A1: PREMISSAS | B1: 44927 | C1: 44958 | D1: 44986 | E1: 45017 | F1: 45047 | G1: 45078 | H1: 45108 | I1: 45139 | J1: 45170 | K1: 45200 | L1: 45231 | M1: 45261 | N1: 45292 | O1: TOTAL
A2: Reune - Fatura | E2: 27744 | F2: 145184 | G2: 130368 | H2: 130368 | I2: 118272 | J2: 47712 | O2: =SUM(D2:M2) -> 599648
A3: Reune- Receita liquida | B3: =B2*(1-B5) -> 0 | C3: =C2*(1-C5) -> 0 | D3: =D2*(1-D5) -> 0 | E3: =E2*(1-E5) -> 26079.36 | F3: =F2*(1-F5) -> 136472.96 | G3: =G2*(1-G5) -> 106901.76 | H3: =H2*(1-H5) -> 106901.76 | I3: =I2*(1-I5) -> 96983.04 | ... M3: =M2*(1-M5) -> 0 | O3: =SUM(D3:M3) -> 512462.72
A5: IMPOSTOS | B5: 0.06 | C5: 0.06 | D5: 0.06 | E5: 0.06 | F5: 0.06 | G5: 0.18 | H5: 0.18 | I5: 0.18 | J5: 0.18 | K5: 0.18 | L5: 0.18 | M5: 0.18 | N5: 0.18
A7: CMV (Custo da Mercadoria Vendida) | B7: 44927 | C7: 44958 | D7: 44986 | E7: 45017 | F7: 45047 | G7: 45078 | H7: 45108 | I7: 45139 | J7: 45170 | K7: 45200 | L7: 45231 | M7: 45261 | N7: 45292 | O7: TOTAL
A8: Reune | B8: =B14 -> 0 | C8: =C14 -> 0 | D8: =D14 -> 0 | E8: =E14 -> 0 | F8: =F14 -> -34000 | G8: =G14 -> -34000 | H8: =H14 -> -44000 | I8: =I14 -> -32000 | ... N8: =N14 -> 0 | O8: =SUM(D8:M8) -> -157096.23 | T8: TBD - Product Manager Senior | U8: 260 | V8: 40 | W8: =V8*U8 -> 10400
T9: TBD - Product Designer Junior | U9: 104 | V9: 40 | W9: =V9*U9 -> 4160
A10: LUCRO (CCI) | B10: 44927 | C10: 44958 | D10: 44986 | E10: 45017 | F10: 45047 | G10: 45078 | H10: 45108 | I10: 45139 | J10: 45170 | K10: 45200 | L10: 45231 | M10: 45261 | N10: 45292 | O10: TOTAL | T10: TBD - Especialista | U10: 240 | V10: 40 | W10: =V10*U10 -> 9600
A11: Reune | B11: =B3+B8 -> 0 | C11: =C3+C8 -> 0 | D11: =D3+D8 -> 0 | E11: =E3+E8 -> 26079.36 | F11: =F3+F8 -> 102472.96 | G11: =G3+G8 -> 72901.76 | H11: =H3+H8 -> 62901.76 | I11: =I3+I8 -> 64983.04 | ... N11: =N3+N8 -> 0 | O11: =SUM(D11:M11) -> 355366.49 | T11: TBD - Dev Pleno | U11: 160 | W11: =V11*U11 -> 0
B12: =B11/B3 -> #DIV/0! | C12: =C11/C3 -> #DIV/0! | D12: =D11/D3 -> #DIV/0! | E12: =E11/E3 -> 1 | F12: =F11/F3 -> 0.7508664 | G12: =G11/G3 -> 0.68195098 | H12: =H11/H3 -> 0.58840715 | I12: =I11/I3 -> 0.6700454 | ... O12: =O11/O3 -> 0.69344847 | T12: TBD - Dev Senior | U12: 180 | W12: =V12*U12 -> 0
W13: =SUM(W8:W12) -> 24160
A14: =A8 -> Reune | B14: =B15+B19+B21 -> 0 | C14: =C15+C19+C21 -> 0 | D14: =D15+D19+D21 -> 0 | E14: =E15+E19+E21 -> 0 | F14: =F15+F19+F21 -> -34000 | G14: =G15+G19+G21 -> -34000 | H14: =H15+H19+H21 -> -44000 | I14: =I15+I19+I21 -> -32000 | ... O14: =O15+O19+O21 -> -157096.23
A15: Desenvolvimento | B15: =SUM(B16:B18) -> 0 | C15: =SUM(C16:C18) -> 0 | D15: =SUM(D16:D18) -> 0 | E15: =SUM(E16:E18) -> 0 | F15: =SUM(F16:F18) -> -31000 | G15: =SUM(G16:G18) -> -31000 | H15: =SUM(H16:H18) -> -41000 | I15: =SUM(I16:I18) -> -25000 | ... N15: =SUM(N16:N18) -> 0 | O15: =SUM(D15:M15) -> -141096.23
A16: Jose Neto | F16: =-VLOOKUP($A$16,'ZH02'!$B:$N,4,0) -> -18000 | G16: =-VLOOKUP($A$16,'ZH02'!$B:$N,4,0) -> -18000 | H16: =-VLOOKUP($A$16,'ZH02'!$B:$N,4,0) -> -18000
A17: Allan Patrick De Freitas Santana | H17: =-VLOOKUP($A$17,'ZH02'!$B:$N,4,0) -> -10000 | I17: -12000 | J17: -6286.71
A18: Arthur | F18: =-VLOOKUP($A$18,'ZH02'!$B:$N,4,0) -> -13000 | G18: =-VLOOKUP($A$18,'ZH02'!$B:$N,4,0) -> -13000 | H18: =-VLOOKUP($A$18,'ZH02'!$B:$N,4,0) -> -13000 | I18: =-VLOOKUP($A$18,'ZH02'!$B:$N,4,0) -> -13000 | J18: -6809.52
A19: Design | B19: =SUM(B20) -> 0 | C19: =SUM(C20) -> 0 | D19: =SUM(D20) -> 0 | E19: =SUM(E20) -> 0 | F19: =SUM(F20) -> -3000 | G19: =SUM(G20) -> -3000 | H19: =SUM(H20) -> -3000 | I19: =SUM(I20) -> 0 | ... N19: =SUM(N20) -> 0 | O19: =SUM(D19:M19) -> -9000
A20: Amanda | F20: =-VLOOKUP($A$20,'ZH02'!$B:$N,4,0) -> -3000 | G20: =-VLOOKUP($A$20,'ZH02'!$B:$N,4,0) -> -3000 | H20: =-VLOOKUP($A$20,'ZH02'!$B:$N,4,0) -> -3000
A21: Outros custos gerais | B21: =SUM(B22:B23) -> 0 | C21: =SUM(C22:C23) -> 0 | D21: =SUM(D22:D23) -> 0 | E21: =SUM(E22:E23) -> 0 | F21: =SUM(F22:F23) -> 0 | G21: =SUM(G22:G23) -> 0 | H21: =SUM(H22:H23) -> 0 | I21: =SUM(I22:I23) -> -7000 | ... N21: =SUM(N22:N23) -> 0 | O21: =SUM(D21:M21) -> -7000
A22: Viagens | I22: -7000
F24: 168

Sheet CREFISA
A1: PREMISSAS | B1: 44927 | C1: 44958 | D1: 44986 | E1: 45017 | F1: 45047 | G1: 45078 | H1: 45108 | I1: 45139 | J1: 45170 | K1: 45200 | L1: 45231 | M1: 45261 | N1: 45292 | O1: TOTAL
A2: Crefisa+ - Faturamento | E2: 52147.2 | F2: 52147.2 | G2: 80704 | H2: 78220.8 | I2: 78220.8 | J2: 78220.8 | K2: 78220.8 | L2: 78220.8 | M2: 78220.8 | O2: =SUM(B2:M2) -> 654323.2
A3: Crefisa+ - Receita liquida | B3: =B2*(1-B5) -> 0 | C3: =SUM(C2:C2)*(1-C5) -> 0 | D3: =SUM(D2:D2)*(1-D5) -> 0 | E3: =SUM(E2:E2)*(1-E5) -> 49018.368 | F3: =SUM(F2:F2)*(1-F5) -> 49018.368 | G3: =SUM(G2:G2)*(1-G5) -> 72633.6 | H3: =SUM(H2:H2)*(1-H5) -> 70398.72 | I3: =SUM(I2:I2)*(1-I5) -> 64141.056 | J3: =SUM(J2:J2)*(1-J5) -> 64141.056 | ... M3: =SUM(M2:M2)*(1-M5) -> 64141.056 | O3: =SUM(B3:M3) -> 561774.34
A5: IMPOSTOS | B5: 0.06 | C5: 0.06 | D5: 0.06 | E5: 0.06 | F5: 0.06 | G5: 0.1 | H5: 0.1 | I5: 0.18 | J5: 0.18 | K5: 0.18 | L5: 0.18 | M5: 0.18 | N5: 0.18
A7: CMV (Custo da Mercadoria Vendida) | B7: 44927 | C7: 44958 | D7: 44986 | E7: 45017 | F7: 45047 | G7: 45078 | H7: 45108 | I7: 45139 | J7: 45170 | K7: 45200 | L7: 45231 | M7: 45261 | N7: 45292 | O7: TOTAL
A8: Crefisa+ | B8: =B14 -> 0 | C8: =C14 -> 0 | D8: =D14 -> 0 | E8: =E14 -> -3100 | F8: =F14 -> -19381 | G8: =G14 -> -23429 | H8: =H14 -> -26714.286 | I8: =I14 -> -30000 | ... N8: =N14 -> -26000 | O8: =SUM(D8:N8) -> -248624.29 | T8: TBD - Sócio | U8: 176 | W8: =V8*U8 -> 0
T9: Raphaela Oliveira | U9: 120 | W9: =V9*U9 -> 0
A10: LUCRO (CCI) | B10: 44927 | C10: 44958 | D10: 44986 | E10: 45017 | F10: 45047 | G10: 45078 | H10: 45108 | I10: 45139 | J10: 45170 | K10: 45200 | L10: 45231 | M10: 45261 | N10: 45292 | O10: TOTAL | T10: Gustavo Rodrigues | U10: 120 | V10: 168 | W10: =V10*U10 -> 20160
A11: Crefisa+ | B11: =B3+B8 -> 0 | C11: =C3+C8 -> 0 | D11: =D3+D8 -> 0 | E11: =E3+E8 -> 45918.368 | F11: =F3+F8 -> 29637.368 | G11: =G3+G8 -> 49204.6 | H11: =H3+H8 -> 43684.434 | I11: =I3+I8 -> 34141.056 | ... N11: =N3+N8 -> -26000 | O11: =SUM(D11:N11) -> 313150.05 | T11: Vinicius | U11: 110.4 | V11: 168 | W11: =V11*U11 -> 18547.2
B12: =B11/B3 -> #DIV/0! | C12: =C11/C3 -> #DIV/0! | D12: =D11/D3 -> #DIV/0! | E12: =E11/E3 -> 0.9367584 | F12: =F11/F3 -> 0.6046176 | G12: =G11/G3 -> 0.67743579 | H12: =H11/H3 -> 0.62052881 | I12: =I11/I3 -> 0.53228085 | ... O12: =O11/O3 -> 0.55743032 | V12: 168 | W12: =V12*U12 -> 0
W13: =SUM(W8:W12) -> 38707.2
A14: =A8 -> Crefisa+ | B14: =B15+B20+B22 -> 0 | C14: =C15+C20+C22 -> 0 | D14: =D15+D20+D22 -> 0 | E14: =E15+E20+E22 -> -3100 | F14: =F15+F20+F22 -> -19381 | G14: =G15+G20+G22 -> -23429 | H14: =H15+H20+H22 -> -26714.286 | I14: =I15+I20+I22 -> -30000 | ... O14: =O15+O20+O22 -> -248624.29
A15: Desenvolvimento | B15: =SUM(B16:B19) -> 0 | C15: =SUM(C16:C19) -> 0 | D15: =SUM(D16:D19) -> 0 | E15: =SUM(E16:E19) -> 0 | F15: =SUM(F16:F19) -> -16000 | G15: =SUM(G16:G19) -> -19429 | H15: =SUM(H16:H19) -> -22714.286 | I15: =SUM(I16:I19) -> -26000 | ... N15: =SUM(N16:N19) -> -26000 | O15: =SUM(D15:N15) -> -214143.29
A16: Gustavo Rodrigues | F16: =-VLOOKUP($A$16,'ZH02'!$B:$N,4,0) -> -8000 | G16: =-VLOOKUP($A$16,'ZH02'!$B:$N,4,0) -> -8000 | H16: =-VLOOKUP($A$16,'ZH02'!$B:$N,4,0) -> -8000 | I16: =-VLOOKUP($A$16,'ZH02'!$B:$N,4,0) -> -8000 | J16: =-VLOOKUP($A$16,'ZH02'!$B:$N,4,0) -> -8000 | K16: =-VLOOKUP($A$16,'ZH02'!$B:$N,4,0) -> -8000 | L16: =-VLOOKUP($A$16,'ZH02'!$B:$N,4,0) -> -8000 | M16: =-VLOOKUP($A$16,'ZH02'!$B:$N,4,0) -> -8000 | N16: =-VLOOKUP($A$16,'ZH02'!$B:$N,4,0) -> -8000
A17: Mateus Chaves | G17: -3429 | H17: =-VLOOKUP($A$17,'ZH02'!$B:$N,4,0) -> -9000 | I17: =-VLOOKUP($A$17,'ZH02'!$B:$N,4,0) -> -9000 | J17: =-VLOOKUP($A$17,'ZH02'!$B:$N,4,0) -> -9000 | K17: =-VLOOKUP($A$17,'ZH02'!$B:$N,4,0) -> -9000 | L17: =-VLOOKUP($A$17,'ZH02'!$B:$N,4,0) -> -9000 | M17: =-VLOOKUP($A$17,'ZH02'!$B:$N,4,0) -> -9000 | N17: =-VLOOKUP($A$17,'ZH02'!$B:$N,4,0) -> -9000
A18: Ericsson Teixeira | I18: =-VLOOKUP($A$18,'ZH02'!$B:$N,4,0) -> -9000 | J18: =-VLOOKUP($A$18,'ZH02'!$B:$N,4,0) -> -9000 | K18: =-VLOOKUP($A$18,'ZH02'!$B:$N,4,0) -> -9000 | L18: =-VLOOKUP($A$18,'ZH02'!$B:$N,4,0) -> -9000 | M18: =-VLOOKUP($A$18,'ZH02'!$B:$N,4,0) -> -9000 | N18: =-VLOOKUP($A$18,'ZH02'!$B:$N,4,0) -> -9000
A19: Matheus Alcatrao | F19: =-VLOOKUP($A$19,'ZH02'!$B:$N,4,0) -> -8000 | G19: =-VLOOKUP($A$19,'ZH02'!$B:$N,4,0) -> -8000 | H19: -5714.2857
A20: Design | B20: =SUM(B21) -> 0 | C20: =SUM(C21) -> 0 | D20: =SUM(D21) -> 0 | E20: =SUM(E21) -> 0 | F20: =SUM(F21) -> 0 | G20: =SUM(G21) -> 0 | H20: =SUM(H21) -> 0 | I20: =SUM(I21) -> 0 | ... N20: =SUM(N21) -> 0 | O20: =SUM(D20:M20) -> 0
A21: TBD - Sócio | C21: =-VLOOKUP($A$21,'ZH02'!$B:$N,4,0) -> 0 | D21: =-VLOOKUP($A$21,'ZH02'!$B:$N,4,0) -> 0 | E21: =-VLOOKUP($A$21,'ZH02'!$B:$N,4,0) -> 0 | F21: =-VLOOKUP($A$21,'ZH02'!$B:$N,4,0) -> 0 | G21: =-VLOOKUP($A$21,'ZH02'!$B:$N,4,0) -> 0
A22: Outros custos gerais | B22: =SUM(B23:B24) -> 0 | C22: =SUM(C23:C24) -> 0 | D22: =SUM(D23:D24) -> 0 | E22: =SUM(E23:E24) -> -3100 | F22: =SUM(F23:F24) -> -3381 | G22: =SUM(G23:G24) -> -4000 | H22: =SUM(H23:H24) -> -4000 | I22: =SUM(I23:I24) -> -4000 | ... N22: =SUM(N23:N24) -> 0 | O22: =SUM(D22:N22) -> -34481
A23: Custo alocado no cliente | E23: -3100 | F23: -3381 | G23: -4000 | H23: -4000 | I23: -4000 | J23: -4000 | K23: -4000 | L23: -4000 | M23: -4000
A24: VPN

Sheet COGNA - KEEGGO
A1: PREMISSAS | B1: 44927 | C1: 44958 | D1: 44986 | E1: 45017 | F1: 45047 | G1: 45078 | H1: 45108 | I1: 45139 | J1: 45170 | K1: 45200 | L1: 45231 | M1: 45261 | N1: 45292 | O1: TOTAL
A2: Crefisa+ - Faturamento | F2: 50400 | G2: 50400 | H2: 50400 | I2: 50400 | J2: 50400 | K2: 50400 | L2: 50400 | M2: 50400 | O2: =SUM(B2:M2) -> 403200
A3: Captar - Receita liquida | B3: =B2*(1-B5) -> 0 | C3: =SUM(C2:C2)*(1-C5) -> 0 | D3: =SUM(D2:D2)*(1-D5) -> 0 | E3: =SUM(E2:E2)*(1-E5) -> 0 | F3: =SUM(F2:F2)*(1-F5) -> 47376 | G3: =SUM(G2:G2)*(1-G5) -> 46368 | H3: =SUM(H2:H2)*(1-H5) -> 41328 | I3: =SUM(I2:I2)*(1-I5) -> 41328 | J3: =SUM(J2:J2)*(1-J5) -> 41328 | ... M3: =SUM(M2:M2)*(1-M5) -> 41328 | O3: =SUM(B3:M3) -> 341712
A5: IMPOSTOS | B5: 0.06 | C5: 0.06 | D5: 0.06 | E5: 0.06 | F5: 0.06 | G5: 0.08 | H5: 0.18 | I5: 0.18 | J5: 0.18 | K5: 0.18 | L5: 0.18 | M5: 0.18 | N5: 0.18
A7: CMV (Custo da Mercadoria Vendida) | B7: 44927 | C7: 44958 | D7: 44986 | E7: 45017 | F7: 45047 | G7: 45078 | H7: 45108 | I7: 45139 | J7: 45170 | K7: 45200 | L7: 45231 | M7: 45261 | N7: 45292 | O7: TOTAL
A8: Captar | B8: =B14 -> 0 | C8: =C14 -> 0 | D8: =D14 -> 0 | E8: =E14 -> 0 | F8: =F14 -> 0 | G8: =G14 -> -15000 | H8: =H14 -> -16000 | I8: =I14 -> -15000 | ... N8: =N14 -> 0 | O8: =SUM(D8:N8) -> -106000 | T8: TBD - Sócio | U8: 176 | W8: =V8*U8 -> 0
T9: Raphaela Oliveira | U9: 120 | W9: =V9*U9 -> 0
A10: LUCRO (CCI) | B10: 44927 | C10: 44958 | D10: 44986 | E10: 45017 | F10: 45047 | G10: 45078 | H10: 45108 | I10: 45139 | J10: 45170 | K10: 45200 | L10: 45231 | M10: 45261 | N10: 45292 | O10: TOTAL | T10: Gustavo Rodrigues | U10: 120 | V10: 168 | W10: =V10*U10 -> 20160
A11: Captar | B11: =B3+B8 -> 0 | C11: =C3+C8 -> 0 | D11: =D3+D8 -> 0 | E11: =E3+E8 -> 0 | F11: =F3+F8 -> 47376 | G11: =G3+G8 -> 31368 | H11: =H3+H8 -> 25328 | I11: =I3+I8 -> 26328 | ... N11: =N3+N8 -> 0 | O11: =SUM(D11:N11) -> 235712 | T11: Vinicius | U11: 110.4 | V11: 168 | W11: =V11*U11 -> 18547.2
B12: =B11/B3 -> #DIV/0! | C12: =C11/C3 -> #DIV/0! | D12: =D11/D3 -> #DIV/0! | E12: =E11/E3 -> #DIV/0! | F12: =F11/F3 -> 1 | G12: =G11/G3 -> 0.67650104 | H12: =H11/H3 -> 0.61285327 | I12: =I11/I3 -> 0.63704994 | ... O12: =O11/O3 -> 0.68979726 | V12: 168 | W12: =V12*U12 -> 0
W13: =SUM(W8:W12) -> 38707.2
A14: =A8 -> Captar | B14: =B15+B19+B21 -> 0 | C14: =C15+C19+C21 -> 0 | D14: =D15+D19+D21 -> 0 | E14: =E15+E19+E21 -> 0 | F14: =F15+F19+F21 -> 0 | G14: =G15+G19+G21 -> -15000 | H14: =H15+H19+H21 -> -16000 | I14: =I15+I19+I21 -> -15000 | ... O14: =O15+O19+O21 -> -106000
A15: Desenvolvimento | B15: =SUM(B16:B18) -> 0 | C15: =SUM(C16:C18) -> 0 | D15: =SUM(D16:D18) -> 0 | E15: =SUM(E16:E18) -> 0 | F15: =SUM(F16:F18) -> 0 | G15: =SUM(G16:G18) -> -15000 | H15: =SUM(H16:H18) -> -15000 | I15: =SUM(I16:I18) -> -15000 | ... N15: =SUM(N16:N18) -> 0 | O15: =SUM(D15:N15) -> -105000
A16: Nathan Santos | G16: =-VLOOKUP($A$16,'ZH02'!$B:$N,4,0) -> -15000 | H16: =-VLOOKUP($A$16,'ZH02'!$B:$N,4,0) -> -15000 | I16: =-VLOOKUP($A$16,'ZH02'!$B:$N,4,0) -> -15000 | J16: =-VLOOKUP($A$16,'ZH02'!$B:$N,4,0) -> -15000 | K16: =-VLOOKUP($A$16,'ZH02'!$B:$N,4,0) -> -15000 | L16: =-VLOOKUP($A$16,'ZH02'!$B:$N,4,0) -> -15000 | M16: =-VLOOKUP($A$16,'ZH02'!$B:$N,4,0) -> -15000
A17: TBD - Sócio | H17: =-VLOOKUP($A$17,'ZH02'!$B:$N,4,0) -> 0 | I17: =-VLOOKUP($A$17,'ZH02'!$B:$N,4,0) -> 0 | J17: =-VLOOKUP($A$17,'ZH02'!$B:$N,4,0) -> 0 | K17: =-VLOOKUP($A$17,'ZH02'!$B:$N,4,0) -> 0 | L17: =-VLOOKUP($A$17,'ZH02'!$B:$N,4,0) -> 0 | M17: =-VLOOKUP($A$17,'ZH02'!$B:$N,4,0) -> 0 | N17: =-VLOOKUP($A$17,'ZH02'!$B:$N,4,0) -> 0
A18: TBD - Sócio | F18: =-VLOOKUP($A$18,'ZH02'!$B:$N,4,0) -> 0 | G18: =-VLOOKUP($A$18,'ZH02'!$B:$N,4,0) -> 0 | H18: =-VLOOKUP($A$18,'ZH02'!$B:$N,4,0) -> 0 | I18: =-VLOOKUP($A$18,'ZH02'!$B:$N,4,0) -> 0 | J18: =-VLOOKUP($A$18,'ZH02'!$B:$N,4,0) -> 0 | K18: =-VLOOKUP($A$18,'ZH02'!$B:$N,4,0) -> 0 | L18: =-VLOOKUP($A$18,'ZH02'!$B:$N,4,0) -> 0 | M18: =-VLOOKUP($A$18,'ZH02'!$B:$N,4,0) -> 0 | N18: =-VLOOKUP($A$18,'ZH02'!$B:$N,4,0) -> 0
A19: Design | B19: =SUM(B20) -> 0 | C19: =SUM(C20) -> 0 | D19: =SUM(D20) -> 0 | E19: =SUM(E20) -> 0 | F19: =SUM(F20) -> 0 | G19: =SUM(G20) -> 0 | H19: =SUM(H20) -> 0 | I19: =SUM(I20) -> 0 | ... N19: =SUM(N20) -> 0 | O19: =SUM(D19:M19) -> 0
A20: TBD - Sócio | C20: =-VLOOKUP($A$20,'ZH02'!$B:$N,4,0) -> 0 | D20: =-VLOOKUP($A$20,'ZH02'!$B:$N,4,0) -> 0 | E20: =-VLOOKUP($A$20,'ZH02'!$B:$N,4,0) -> 0 | F20: =-VLOOKUP($A$20,'ZH02'!$B:$N,4,0) -> 0 | G20: =-VLOOKUP($A$20,'ZH02'!$B:$N,4,0) -> 0
A21: Outros custos gerais | B21: =SUM(B22:B23) -> 0 | C21: =SUM(C22:C23) -> 0 | D21: =SUM(D22:D23) -> 0 | E21: =SUM(E22:E23) -> 0 | F21: =SUM(F22:F23) -> 0 | G21: =SUM(G22:G23) -> 0 | H21: =SUM(H22:H23) -> -1000 | I21: =SUM(I22:I23) -> 0 | ... N21: =SUM(N22:N23) -> 0 | O21: =SUM(D21:N21) -> -1000
A22: conserto do note | H22: -1000
A23: VPN

Sheet LPs
A1: PREMISSAS | B1: 44986 | C1: 45017 | D1: 45047 | E1: 45078 | F1: 45108 | G1: 45139 | H1: 45170 | I1: 45200 | J1: 45231 | K1: 45261 | L1: TOTAL
A2: RECONHECIMENTO | B2: =SUM(B3:B8) -> 0 | C2: =SUM(C3:C8) -> 8100 | D2: =SUM(D3:D8) -> 30900 | E2: =SUM(E3:E8) -> 2500 | F2: =SUM(F3:F8) -> 2500 | G2: =SUM(G3:G8) -> 0 | H2: =SUM(H3:H8) -> 0 | I2: =SUM(I3:I8) -> 0 | ... K2: =SUM(K3:K8) -> 0 | L2: =SUM(B2:K2) -> 44000
A3: Geonoma | B3: R$ - | C3: 5600 | D3: 8400 | F3: 0 | G3: 0 | H3: 0 | I3: 0 | J3: 0 | K3: 0 | L3: =SUM(B3:K3) -> 14000 | O3: 5600 | P3: =O3*6% -> 336
A4: VIP financeira | B4: R$ - | D4: 20000 | E4: 0 | F4: 0 | G4: 0 | H4: 0 | I4: 0 | J4: 0 | K4: 0 | L4: =SUM(B4:K4) -> 20000 | O4: 2500 | P4: =O4*6% -> 150
A5: Warren | B5: R$ - | C5: 2500 | D5: 2500 | E5: 2500 | F5: 2500 | H5: 0 | I5: 0 | J5: 0 | K5: 0 | L5: =SUM(B5:K5) -> 10000 | O5: 49606.4 | P5: =O5*6% -> 2976.384
B6: R$ - | C6: 0 | D6: 0 | E6: 0 | F6: 0 | G6: 0 | H6: 0 | I6: 0 | J6: 0 | K6: 0 | L6: =SUM(B6:K6) -> 0
B7: R$ - | C7: 0 | D7: 0 | E7: 0 | F7: 0 | G7: 0 | H7: 0 | I7: 0 | J7: 0 | K7: 0 | L7: =SUM(B7:K7) -> 0
B8: R$ - | C8: 0 | D8: 0 | E8: 0 | F8: 0 | G8: 0 | H8: 0 | I8: 0 | J8: 0 | K8: 0 | L8: =SUM(B8:K8) -> 0
A9: Receita Liquida | B9: =B2*(1-B11) -> 0 | C9: =C2*(1-C11) -> 7614 | D9: =D2*(1-D11) -> 28428 | E9: =E2*(1-E11) -> 2300 | F9: =F2*(1-F11) -> 2300 | G9: =G2*(1-G11) -> 0 | H9: =H2*(1-H11) -> 0 | I9: =I2*(1-I11) -> 0 | ... K9: =K2*(1-K11) -> 0 | L9: =SUM(B9:K9) -> 40642
A11: IMPOSTOS | B11: 0.06 | C11: 0.06 | D11: 0.08 | E11: 0.08 | F11: 0.08 | G11: 0.06 | H11: 0.06 | I11: 0.06 | J11: 0.06 | K11: 0.06
A13: CMV (Custo da Mercadoria Vendida) | B13: 44986 | C13: 45017 | D13: 45047 | E13: 45078 | F13: 45108 | G13: 45139 | H13: 45170 | I13: 45200 | J13: 45231 | K13: 45261 | L13: TOTAL
A14: Geonoma | B14: R$ - | C14: =C34 -> -1500 | D14: =D34 -> 0 | E14: =E34 -> 0 | F14: =F34 -> 0 | G14: =G34 -> 0 | H14: =H34 -> 0 | I14: =I34 -> 0 | J14: =J34 -> 0 | K14: =K34 -> 0 | L14: =SUM(B14:K14) -> -1500
A15: VIP financeira | B15: R$ - | C15: -1000 | D15: =D39 -> 0 | E15: =E39 -> 0 | F15: =F39 -> 0 | G15: =G39 -> 0 | H15: =H39 -> 0 | I15: =I39 -> 0 | J15: =J39 -> 0 | K15: =K39 -> 0 | L15: =SUM(B15:K15) -> -1000
A16: Warren | B16: R$ - | C16: =C44 -> 0 | D16: =D44 -> -1000 | E16: =E44 -> -1200 | F16: =F44 -> -1200 | G16: =G44 -> 0 | H16: =H44 -> 0 | I16: =I44 -> 0 | J16: =J44 -> 0 | K16: =K44 -> 0 | L16: =SUM(B16:K16) -> -3400
A17: 0 | B17: R$ - | C17: =C49 -> 0 | D17: =D49 -> 0 | E17: =E49 -> 0 | F17: =F49 -> 0 | G17: =G49 -> 0 | H17: =H49 -> 0 | I17: =I49 -> 0 | J17: =J49 -> 0 | K17: =K49 -> 0 | L17: =SUM(B17:K17) -> 0
A18: 0 | B18: R$ - | C18: =C54 -> 0 | D18: =D54 -> 0 | E18: =E54 -> 0 | F18: =F54 -> 0 | G18: =G54 -> 0 | H18: =H54 -> 0 | I18: =I54 -> 0 | J18: =J54 -> 0 | K18: =K54 -> 0 | L18: =SUM(B18:K18) -> 0
A19: 0 | B19: R$ - | C19: =C59 -> 0 | D19: =D59 -> 0 | E19: =E59 -> 0 | F19: =F59 -> 0 | G19: =G59 -> 0 | H19: =H59 -> 0 | I19: =I59 -> 0 | J19: =J59 -> 0 | K19: =K59 -> 0 | L19: =SUM(B19:K19) -> 0
B20: =SUM(B14:B19) -> 0 | C20: =SUM(C14:C19) -> -2500 | D20: =SUM(D14:D19) -> -1000 | E20: =SUM(E14:E19) -> -1200 | F20: =SUM(F14:F19) -> -1200 | G20: =SUM(G14:G19) -> 0 | H20: =SUM(H14:H19) -> 0 | I20: =SUM(I14:I19) -> 0 | ... K20: =SUM(K14:K19) -> 0 | L20: =SUM(B20:K20) -> -5900
A23: LUCRO (CCI) | B23: 44986 | C23: 45017 | D23: 45047 | E23: 45078 | F23: 45108 | G23: 45139 | H23: 45170 | I23: 45200 | J23: 45231 | K23: 45261 | L23: TOTAL
A24: Geonoma | B24: R$ - | C24: =C3*(1-C$11)+C14 -> 3764 | D24: =D3*(1-D$11)+D14 -> 7728 | E24: =E3*(1-E$11)+E14 -> 0 | F24: =F3*(1-F$11)+F14 -> 0 | G24: =G3*(1-G$11)+G14 -> 0 | H24: =H3*(1-H$11)+H14 -> 0 | I24: =I3*(1-I$11)+I14 -> 0 | J24: =J3*(1-J$11)+J14 -> 0 | K24: =K3*(1-K$11)+K14 -> 0 | L24: =SUM(B24:K24) -> 11492
A25: VIP financeira | B25: R$ - | C25: =C4*(1-C$11)+C15 -> -1000 | D25: =D4*(1-D$11)+D15 -> 18400 | E25: =E4*(1-E$11)+E15 -> 0 | F25: =F4*(1-F$11)+F15 -> 0 | G25: =G4*(1-G$11)+G15 -> 0 | H25: =H4*(1-H$11)+H15 -> 0 | I25: =I4*(1-I$11)+I15 -> 0 | J25: =J4*(1-J$11)+J15 -> 0 | K25: =K4*(1-K$11)+K15 -> 0 | L25: =SUM(B25:K25) -> 17400
A26: Warren | B26: R$ - | C26: =C5*(1-C$11)+C16 -> 2350 | D26: =D5*(1-D$11)+D16 -> 1300 | E26: =E5*(1-E$11)+E16 -> 1100 | F26: =F5*(1-F$11)+F16 -> 1100 | G26: =G5*(1-G$11)+G16 -> 0 | H26: =H5*(1-H$11)+H16 -> 0 | I26: =I5*(1-I$11)+I16 -> 0 | J26: =J5*(1-J$11)+J16 -> 0 | K26: =K5*(1-K$11)+K16 -> 0 | L26: =SUM(B26:K26) -> 5850
A27: 0 | B27: R$ - | C27: =C6*(1-C$11)+C17 -> 0 | D27: =D6*(1-D$11)+D17 -> 0 | E27: =E6*(1-E$11)+E17 -> 0 | F27: =F6*(1-F$11)+F17 -> 0 | G27: =G6*(1-G$11)+G17 -> 0 | H27: =H6*(1-H$11)+H17 -> 0 | I27: =I6*(1-I$11)+I17 -> 0 | J27: =J6*(1-J$11)+J17 -> 0 | K27: =K6*(1-K$11)+K17 -> 0 | L27: =SUM(B27:K27) -> 0
A28: 0 | B28: R$ - | C28: =C7*(1-C$11)+C18 -> 0 | D28: =D7*(1-D$11)+D18 -> 0 | E28: =E7*(1-E$11)+E18 -> 0 | F28: =F7*(1-F$11)+F18 -> 0 | G28: =G7*(1-G$11)+G18 -> 0 | H28: =H7*(1-H$11)+H18 -> 0 | I28: =I7*(1-I$11)+I18 -> 0 | J28: =J7*(1-J$11)+J18 -> 0 | K28: =K7*(1-K$11)+K18 -> 0 | L28: =SUM(B28:K28) -> 0
A29: 0 | B29: R$ - | C29: =C8*(1-C$11)+C19 -> 0 | D29: =D8*(1-D$11)+D19 -> 0 | E29: =E8*(1-E$11)+E19 -> 0 | F29: =F8*(1-F$11)+F19 -> 0 | G29: =G8*(1-G$11)+G19 -> 0 | H29: =H8*(1-H$11)+H19 -> 0 | I29: =I8*(1-I$11)+I19 -> 0 | J29: =J8*(1-J$11)+J19 -> 0 | K29: =K8*(1-K$11)+K19 -> 0 | L29: =SUM(B29:K29) -> 0
B30: =SUM(B24:B29) -> 0 | C30: =SUM(C24:C29) -> 5114 | D30: =SUM(D24:D29) -> 27428 | E30: =SUM(E24:E29) -> 1100 | F30: =SUM(F24:F29) -> 1100 | G30: =SUM(G24:G29) -> 0 | H30: =SUM(H24:H29) -> 0 | I30: =SUM(I24:I29) -> 0 | ... K30: =SUM(K24:K29) -> 0 | L30: =SUM(B30:K30) -> 34742
A34: Geonoma | B34: R$ - | C34: =SUM(C35:C37) -> -1500 | D34: =SUM(D35:D37) -> 0 | E34: =SUM(E35:E37) -> 0 | F34: =SUM(F35:F37) -> 0 | G34: =SUM(G35:G37) -> 0 | H34: =SUM(H35:H37) -> 0 | I34: =SUM(I35:I37) -> 0 | J34: =SUM(J35:J37) -> 0 | K34: =SUM(K35:K37) -> 0 | L34: =SUM(B34:K34) -> -1500
A35: Desenvolvedor - No/low code | B35: R$ - | D35: R$ - | E35: R$ - | F35: R$ - | G35: R$ - | H35: R$ - | I35: R$ - | J35: R$ - | K35: R$ - | L35: R$ -
A36: Design | B36: R$ - | C36: -1000 | D36: R$ - | E36: R$ - | F36: R$ - | G36: R$ - | H36: R$ - | I36: R$ - | J36: R$ - | K36: R$ - | L36: R$ -
A37: Outros custos gerais | B37: R$ - | C37: -500 | D37: R$ - | E37: R$ - | F37: R$ - | G37: R$ - | H37: R$ - | I37: R$ - | J37: R$ - | K37: R$ -
A39: VIP financeira | B39: R$ - | C39: =SUM(C40:C42) -> -400 | D39: =SUM(D40:D42) -> 0 | E39: =SUM(E40:E42) -> 0 | F39: =SUM(F40:F42) -> 0 | G39: =SUM(G40:G42) -> 0 | H39: =SUM(H40:H42) -> 0 | I39: =SUM(I40:I42) -> 0 | J39: =SUM(J40:J42) -> 0 | K39: =SUM(K40:K42) -> 0 | L39: =SUM(B39:K39) -> -400
A40: Desenvolvedor - No/low code | B40: R$ - | C40: R$ - | D40: R$ - | E40: R$ - | F40: R$ - | G40: R$ - | H40: R$ - | I40: R$ - | J40: R$ - | K40: R$ - | L40: R$ -
A41: Design | B41: R$ - | C41: R$ - | E41: R$ - | F41: R$ - | G41: R$ - | H41: R$ - | I41: R$ - | J41: R$ - | K41: R$ - | L41: R$ -
A42: Outros custos gerais | B42: R$ - | C42: -400 | D42: R$ - | E42: R$ - | F42: R$ - | G42: R$ - | H42: R$ - | I42: R$ - | J42: R$ - | K42: R$ -
A44: Warren | B44: R$ - | C44: =SUM(C45:C47) -> 0 | D44: =SUM(D45:D47) -> -1000 | E44: =SUM(E45:E47) -> -1200 | F44: =SUM(F45:F47) -> -1200 | G44: =SUM(G45:G47) -> 0 | H44: =SUM(H45:H47) -> 0 | I44: =SUM(I45:I47) -> 0 | J44: =SUM(J45:J47) -> 0 | K44: =SUM(K45:K47) -> 0 | L44: =SUM(B44:K44) -> -3400
A45: Desenvolvedor - No/low code | B45: R$ - | C45: R$ - | D45: R$ - | E45: -1200 | F45: -1200 | G45: R$ - | H45: R$ - | I45: R$ - | J45: R$ - | K45: R$ - | L45: R$ -
A46: Design | B46: R$ - | C46: R$ - | D46: -1000 | E46: R$ - | F46: R$ - | G46: R$ - | H46: R$ - | I46: R$ - | J46: R$ - | K46: R$ - | L46: R$ -
A47: Outros custos gerais | B47: R$ - | C47: R$ - | E47: R$ - | F47: R$ - | G47: R$ - | H47: R$ - | I47: R$ - | J47: R$ - | K47: R$ -
A49: 0 | B49: R$ - | C49: =SUM(C50:C52) -> 0 | D49: =SUM(D50:D52) -> 0 | E49: =SUM(E50:E52) -> 0 | F49: =SUM(F50:F52) -> 0 | G49: =SUM(G50:G52) -> 0 | H49: =SUM(H50:H52) -> 0 | I49: =SUM(I50:I52) -> 0 | J49: =SUM(J50:J52) -> 0 | K49: =SUM(K50:K52) -> 0 | L49: =SUM(B49:K49) -> 0
A50: Desenvolvedor - No/low code | B50: R$ - | C50: R$ - | D50: R$ - | E50: R$ - | F50: R$ - | G50: R$ - | H50: R$ - | I50: R$ - | J50: R$ - | K50: R$ - | L50: R$ -
A51: Design | B51: R$ - | C51: R$ - | D51: R$ - | E51: R$ - | F51: R$ - | G51: R$ - | H51: R$ - | I51: R$ - | J51: R$ - | K51: R$ - | L51: R$ -
A52: Outros custos gerais | B52: R$ - | C52: R$ - | D52: R$ - | E52: R$ - | F52: R$ - | G52: R$ - | H52: R$ - | I52: R$ - | J52: R$ - | K52: R$ - | L52: R$ -
A54: 0 | B54: R$ - | C54: =SUM(C55:C57) -> 0 | D54: =SUM(D55:D57) -> 0 | E54: =SUM(E55:E57) -> 0 | F54: =SUM(F55:F57) -> 0 | G54: =SUM(G55:G57) -> 0 | H54: =SUM(H55:H57) -> 0 | I54: =SUM(I55:I57) -> 0 | J54: =SUM(J55:J57) -> 0 | K54: =SUM(K55:K57) -> 0 | L54: =SUM(B54:K54) -> 0
A55: Desenvolvedor - No/low code | B55: R$ - | C55: R$ - | D55: R$ - | E55: R$ - | F55: R$ - | G55: R$ - | H55: R$ - | I55: R$ - | J55: R$ - | K55: R$ - | L55: R$ -
A56: Design | B56: R$ - | C56: R$ - | D56: R$ - | E56: R$ - | F56: R$ - | G56: R$ - | H56: R$ - | I56: R$ - | J56: R$ - | K56: R$ - | L56: R$ -
A57: Outros custos gerais | B57: R$ - | C57: R$ - | D57: R$ - | E57: R$ - | F57: R$ - | G57: R$ - | H57: R$ - | I57: R$ - | J57: R$ - | K57: R$ - | L57: R$ -
A59: 0 | B59: R$ - | C59: =SUM(C60:C62) -> 0 | D59: =SUM(D60:D62) -> 0 | E59: =SUM(E60:E62) -> 0 | F59: =SUM(F60:F62) -> 0 | G59: =SUM(G60:G62) -> 0 | H59: =SUM(H60:H62) -> 0 | I59: =SUM(I60:I62) -> 0 | J59: =SUM(J60:J62) -> 0 | K59: =SUM(K60:K62) -> 0 | L59: =SUM(B59:K59) -> 0
A60: Desenvolvedor - No/low code | B60: R$ - | C60: R$ - | D60: R$ - | E60: R$ - | F60: R$ - | G60: R$ - | H60: R$ - | I60: R$ - | J60: R$ - | K60: R$ - | L60: R$ -
A61: Design | B61: R$ - | C61: R$ - | D61: R$ - | E61: R$ - | F61: R$ - | G61: R$ - | H61: R$ - | I61: R$ - | J61: R$ - | K61: R$ - | L61: R$ -
A62: Outros custos gerais | B62: R$ - | C62: R$ - | D62: R$ - | E62: R$ - | F62: R$ - | G62: R$ - | H62: R$ - | I62: R$ - | J62: R$ - | K62: R$ - | L62: R$ -

Sheet RESUMO PROJETOS
A1: Orla Projetos | B1: 44927 | C1: 44958 | D1: 44986 | E1: 45017 | F1: 45047 | G1: 45078 | H1: 45108 | I1: 45139 | J1: 45170 | K1: 45200 | L1: 45231 | M1: 45261 | N1: 45292 | P1: TOTAL
B2: R$ | C2: R$ | D2: R$ | E2: R$ | F2: R$ | G2: R$ | H2: R$ | I2: R$ | J2: R$ | K2: R$ | L2: R$ | M2: R$ | P2: R$
A3: RECEITA LÍQUIDA | B3: =SUM(B4:B8) -> 10170.8 | C3: =SUM(C4:C8) -> 44101.04 | D3: =SUM(D4:D10) -> 57515.216 | E3: =SUM(E4:E10) -> 178296.13 | F3: =SUM(F4:F10) -> 327697.3 | G3: =SUM(G4:G10) -> 334341.04 | H3: =SUM(H4:H10) -> 449534.96 | I3: =SUM(I4:I10) -> 499544.58 | J3: =SUM(J4:J10) -> 413298.18 | K3: =SUM(K4:K10) -> 413053.06 | ... M3: =SUM(M4:M10) -> 396653.06 | N3: =SUM(N4:N8) -> 0 | P3: =SUM(B3:M3) -> 3504458.4
A4: CUPONI | B4: =CUPONI!B3 -> 10170.8 | C4: =CUPONI!C3 -> 6711.6 | D4: =CUPONI!D3 -> 3271.2 | E4: =CUPONI!E3 -> 4850.4 | F4: =CUPONI!F3 -> 10622 | G4: =CUPONI!G3 -> 10622 | H4: =CUPONI!H3 -> 10622 | I4: =CUPONI!I3 -> 4512 | ... M4: =CUPONI!M3 -> 4512 | P4: =SUM(B4:N4) -> 79430
A5: MANI | B5: =MANI!B6 -> 0 | C5: =MANI!C6 -> 37389.44 | D5: =MANI!D6 -> 46630.016 | E5: =MANI!E6 -> 69920 | F5: =MANI!F6 -> 81907.968 | G5: =MANI!G6 -> 50695.68 | H5: =MANI!H6 -> 32148.48 | I5: =MANI!I6 -> 32148.48 | ... M5: =MANI!M6 -> 0 | P5: =SUM(B5:N5) -> 364441.34
A6: ANBIMA REUNE | B6: ='ANBIMA - REUNE'!B3 -> 0 | C6: ='ANBIMA - REUNE'!C3 -> 0 | D6: ='ANBIMA - REUNE'!D3 -> 0 | E6: ='ANBIMA - REUNE'!E3 -> 26079.36 | F6: ='ANBIMA - REUNE'!F3 -> 136472.96 | G6: ='ANBIMA - REUNE'!G3 -> 106901.76 | H6: ='ANBIMA - REUNE'!H3 -> 106901.76 | I6: ='ANBIMA - REUNE'!I3 -> 96983.04 | ... M6: ='ANBIMA - REUNE'!M3 -> 0 | P6: =SUM(B6:N6) -> 512462.72
A7: Anbima SAÍDA DE DADOS | G7: ='ANBIMA - Saida de Dados'!G3 -> 44820 | H7: ='ANBIMA - Saida de Dados'!H3 -> 229464 | I7: ='ANBIMA - Saida de Dados'!I3 -> 301760 | J7: ='ANBIMA - Saida de Dados'!J3 -> 291920 | K7: ='ANBIMA - Saida de Dados'!K3 -> 344400 | L7: ='ANBIMA - Saida de Dados'!L3 -> 311600 | M7: ='ANBIMA - Saida de Dados'!M3 -> 328000 | N7: ='ANBIMA - Saida de Dados'!N3 -> 0 | P7: =SUM(B7:N7) -> 1851964
A8: CREFISA | B8: =CREFISA!B3 -> 0 | C8: =CREFISA!C3 -> 0 | D8: =CREFISA!D3 -> 0 | E8: =CREFISA!E3 -> 49018.368 | F8: =CREFISA!F3 -> 49018.368 | G8: =CREFISA!G3 -> 72633.6 | H8: =CREFISA!H3 -> 70398.72 | I8: =CREFISA!I3 -> 64141.056 | ... M8: =CREFISA!M3 -> 64141.056 | P8: =SUM(B8:N8) -> 561774.34
A9: COGNA - KEEGGO | F9: ='COGNA - KEEGGO'!F3 -> 47376 | G9: ='COGNA - KEEGGO'!G3 -> 46368 | P9: =SUM(B9:N9) -> 93744
A10: LPs -Aleph | D10: =LPs!C9 -> 7614 | E10: =LPs!D9 -> 28428 | F10: =LPs!E9 -> 2300 | G10: =LPs!F9 -> 2300 | H10: =LPs!G9 -> 0 | I10: =LPs!H3*(1-LPs!H11) -> 0 | J10: =LPs!H2*(1-LPs!H11) -> 0 | K10: =LPs!I31 -> 0 | L10: =LPs!J31 -> 0 | M10: =LPs!K31 -> 0 | P10: =SUM(B10:N10) -> 40642
A11: CUSTOS | B11: =SUM(B12:B16) -> -13000 | C11: =SUM(C12:C16) -> -13220 | D11: =SUM(D12:D16) -> -14036 | E11: =SUM(E12:E16) -> -7284 | F11: =SUM(F12:F16) -> -76941 | G11: =SUM(G12:G16) -> -88729 | H11: =SUM(H12:H16) -> -108442.86 | I11: =SUM(I12:I16) -> -195800 | ... N11: =SUM(N12:N16) -> -198300 | P11: =SUM(B11:N11) -> -1498763.4
A12: =A4 -> CUPONI | B12: =CUPONI!B8 -> -13000 | C12: =CUPONI!C8 -> -13220 | D12: =CUPONI!D8 -> -11036 | E12: =CUPONI!E8 -> -1184 | F12: =CUPONI!F8 -> -1560 | G12: =CUPONI!G8 -> -9300 | H12: =CUPONI!H8 -> -9300 | I12: =CUPONI!I8 -> -9300 | ... N12: =CUPONI!N8 -> -2800 | P12: =SUM(B12:N12) -> -81900
A13: =A5 -> MANI | B13: =MANI!B11 -> 0 | C13: =MANI!C11 -> 0 | D13: =MANI!D11 -> -3000 | E13: =MANI!E11 -> -3000 | F13: =MANI!F11 -> -22000 | G13: =MANI!G11 -> -22000 | H13: =MANI!H11 -> -7500 | I13: =MANI!I11 -> 0 | ... N13: =MANI!N11 -> 0 | P13: =SUM(B13:N13) -> -57500
A14: =A6 -> ANBIMA REUNE | B14: ='ANBIMA - REUNE'!B8 -> 0 | C14: ='ANBIMA - REUNE'!C8 -> 0 | D14: ='ANBIMA - REUNE'!D8 -> 0 | E14: ='ANBIMA - REUNE'!E8 -> 0 | F14: ='ANBIMA - REUNE'!F8 -> -34000 | G14: ='ANBIMA - REUNE'!G8 -> -34000 | H14: ='ANBIMA - REUNE'!H8 -> -44000 | I14: ='ANBIMA - REUNE'!I8 -> -32000 | ... N14: ='ANBIMA - REUNE'!N8 -> 0 | P14: =SUM(B14:N14) -> -157096.23
A15: =A7 -> Anbima SAÍDA DE DADOS | H15: ='ANBIMA - Saida de Dados'!H14 -> -20928.576 | I15: ='ANBIMA - Saida de Dados'!I14 -> -124500 | J15: ='ANBIMA - Saida de Dados'!J14 -> -144500 | K15: ='ANBIMA - Saida de Dados'!K14 -> -155214.29 | L15: ='ANBIMA - Saida de Dados'!L14 -> -169500 | M15: ='ANBIMA - Saida de Dados'!M14 -> -169500 | N15: ='ANBIMA - Saida de Dados'!N14 -> -169500 | P15: =SUM(B15:N15) -> -953642.86
A16: =A8 -> CREFISA | B16: =CREFISA!B8 -> 0 | C16: =CREFISA!C8 -> 0 | D16: =CREFISA!D8 -> 0 | E16: =CREFISA!E8 -> -3100 | F16: =CREFISA!F8 -> -19381 | G16: =CREFISA!G8 -> -23429 | H16: =CREFISA!H8 -> -26714.286 | I16: =CREFISA!I8 -> -30000 | ... N16: =CREFISA!N8 -> -26000 | P16: =SUM(B16:N16) -> -248624.29
A17: =A9 -> COGNA - KEEGGO | F17: ='COGNA - KEEGGO'!F8 -> 0 | G17: ='COGNA - KEEGGO'!G8 -> -15000 | P17: =SUM(B17:N17) -> -15000
A18: =A10 -> LPs -Aleph | D18: =LPs!B20 -> 0 | E18: =LPs!C20 -> -2500 | F18: =LPs!D20 -> -1000 | G18: =LPs!E20 -> -1200 | H18: =LPs!F20 -> -1200 | I18: =LPs!G20-LPs!G32 -> 0 | J18: =LPs!H20-LPs!H32 -> 0 | K18: =LPs!I20 -> 0 | L18: =LPs!J20 -> 0 | M18: =LPs!K20 -> 0 | P18: =SUM(B18:N18) -> -5900
A19: (=) LUCRO PROJETOS | B19: =B3+B11 -> -2829.2 | C19: =C3+C11 -> 30881.04 | D19: =D3+D11 -> 43479.216 | E19: =E3+E11 -> 171012.13 | F19: =F3+F11 -> 250756.3 | G19: =G3+G11 -> 245612.04 | H19: =H3+H11 -> 341092.1 | I19: =I3+I11 -> 303744.58 | ... N19: =N3+N11 -> -198300 | P19: =SUM(B19:N19) -> 2005695
A20: MARGEM MENSAL | B20: =B19/B3 -> -0.27816888 | C20: =C19/C3 -> 0.70023383 | D20: =D19/D3 -> 0.75596023 | E20: =E19/E3 -> 0.95914662 | F20: =F19/F3 -> 0.7652071 | G20: =G19/G3 -> 0.73461529 | H20: =H19/H3 -> 0.75876657 | I20: =I19/I3 -> 0.60804299 | ... N20: =N19/N3 -> #DIV/0! | P20: =P19/P3 -> 0.57232667
A21: MARGEM PROJETADA PELO FATURAMENTO | B21: =(B3+SUM('DRE ORLA 2023'!B23:B72))/B3 -> -4.6170046 | C21: =(C3+SUM('DRE ORLA 2023'!C23:C72))/C3 -> -0.26838573 | D21: =(D3+SUM('DRE ORLA 2023'!D23:D72))/D3 -> -0.069770128 | E21: =(E3+SUM('DRE ORLA 2023'!E23:E72))/E3 -> 0.65614054 | F21: =(F3+SUM('DRE ORLA 2023'!F23:F72))/F3 -> 0.067796916 | G21: =(G3+SUM('DRE ORLA 2023'!G23:G72))/G3 -> -0.2841399 | H21: =(H3+SUM('DRE ORLA 2023'!H23:H72))/H3 -> -0.29167385 | I21: =(I3+SUM('DRE ORLA 2023'!I23:I72))/I3 -> -0.56907072 | ... M21: =(M3+SUM('DRE ORLA 2023'!M23:M72))/M3 -> -1.0604171 | N21: =(N3+'DRE ORLA 2023'!N84)/N3 -> #DIV/0!

Sheet DRE ORLA 2023
A1: Orla Operação | B1: 44927 | C1: 44958 | D1: 44986 | E1: 45017 | F1: 45047 | G1: 45078 | H1: 45108 | I1: 45139 | J1: 45170 | K1: 45200 | L1: 45231 | M1: 45261 | N1: 45292 | O1: 45323 | Q1: TOTAL
B2: R$ | C2: R$ | D2: R$ | E2: R$ | F2: R$ | G2: R$ | H2: R$ | I2: R$ | J2: R$ | K2: R$ | L2: R$ | M2: R$ | N2: R$ | O2: R$
A3: RECEITA (previsão de pagamento) | B3: =SUM(B4:B11) -> 0 | C3: =SUM(C4:C11) -> 13425 | D3: =SUM(D4:D11) -> 50596 | E3: =SUM(E4:E11) -> 64846.4 | F3: =SUM(F4:F11) -> 110380 | G3: =SUM(G4:G11) -> 373912.8 | H3: =SUM(H4:H11) -> 330376 | I3: =SUM(I4:I11) -> 350052.8 | ... O3: =SUM(O4:O11) -> 332800 | Q3: =SUM(B3:O3) -> 3742849
A4: CUPONI | D4: =CUPONI!B2 -> 10820 | E4: =CUPONI!C2 -> 7140 | F4: =CUPONI!D2 -> 3480 | G4: =CUPONI!E2 -> 5160 | H4: =CUPONI!F2 -> 11300 | I4: =CUPONI!G2 -> 11300 | J4: =CUPONI!H2 -> 11300 | K4: =CUPONI!I2 -> 4800 | ... O4: =CUPONI!M2 -> 4800 | Q4: =SUM(B4:O4) -> 84500
A5: MANIPULAE | D5: =MANI!C2 -> 39776 | E5: =MANI!D2 -> 49606.4 | F5: =MANI!E2 -> 76000 | G5: =MANI!F2 -> 89030.4 | H5: =MANI!G2 -> 55104 | I5: =MANI!H2 -> 34944 | J5: =MANI!I2 -> 34944 | K5: =MANI!J2 -> 14784 | ... O5: =MANI!N2 -> 0 | Q5: =SUM(B5:O5) -> 394188.8
A6: ANBIMA - REUNE | G6: ='ANBIMA - REUNE'!F2+'ANBIMA - REUNE'!E2 -> 172928 | H6: ='ANBIMA - REUNE'!G2 -> 130368 | I6: ='ANBIMA - REUNE'!H2 -> 130368 | J6: ='ANBIMA - REUNE'!I2 -> 118272 | K6: ='ANBIMA - REUNE'!J2 -> 47712 | L6: ='ANBIMA - REUNE'!K2 -> 0 | M6: ='ANBIMA - REUNE'!L2 -> 0 | N6: ='ANBIMA - REUNE'!M2 -> 0 | O6: ='ANBIMA - REUNE'!N2 -> 0 | Q6: =SUM(B6:O6) -> 599648
A7: ANBIMA - SAIDA DE DADOS | I7: ='RESUMO PROJETOS'!G7 -> 44820 | J7: ='RESUMO PROJETOS'!H7 -> 229464 | K7: ='RESUMO PROJETOS'!I7 -> 301760 | L7: ='RESUMO PROJETOS'!J7 -> 291920 | M7: ='RESUMO PROJETOS'!K7 -> 344400 | N7: ='RESUMO PROJETOS'!L7 -> 311600 | O7: ='RESUMO PROJETOS'!M7 -> 328000 | Q7: =SUM(B7:O7) -> 1851964
A8: CREFISA | G8: =CREFISA!E2+CREFISA!F2 -> 104294.4 | H8: =CREFISA!G2 -> 80704 | I8: =CREFISA!H2 -> 78220.8 | J8: =CREFISA!I2 -> 78220.8 | K8: =CREFISA!J2 -> 78220.8 | L8: =CREFISA!K2 -> 78220.8 | M8: =CREFISA!L2 -> 78220.8 | N8: =CREFISA!M2 -> 78220.8 | O8: =CREFISA!N2 -> 0 | Q8: =SUM(B8:O8) -> 654323.2
A9: PIQCOIN | C9: 13425 | Q9: =SUM(B9:O9) -> 13425
A10: COGNA - KEEGGO | H10: ='COGNA - KEEGGO'!F2 -> 50400 | I10: ='COGNA - KEEGGO'!G2 -> 50400
A11: LPs | E11: =LPs!C2 -> 8100 | F11: =LPs!D2 -> 30900 | G11: =LPs!E2 -> 2500 | H11: =LPs!F2 -> 2500 | I11: =LPs!G2 -> 0 | J11: =LPs!H2 -> 0 | K11: =LPs!I2 -> 0 | L11: =LPs!J2 -> 0 | M11: =LPs!K2 -> 0 | O11: =LPs!M2 -> 0 | Q11: =SUM(B11:O11) -> 44000
A12: IMPOSTO | B12: -1192.71 | C12: -1706.14 | D12: =SUM(B13:B20) -> -649.2 | E12: =SUM(C13:C20) -> -2814.96 | F12: =SUM(D13:D20) -> -3185.184 | G12: =SUM(E13:E20) -> -18927.68 | H12: =SUM(F13:F20) -> -16711.472 | I12: =SUM(G13:G20) -> -38034.224 | J12: =SUM(H13:H20) -> -44022.16 | K12: =SUM(I13:I20) -> -57690.56 | ... O12: =SUM(M13:M20) -> -82767.744 | Q12: =SUM(B12:O12) -> -526496.15 | R12: =Q12/Q3 -> -0.14066722
A13: =A4 -> CUPONI | B13: =-CUPONI!B2+CUPONI!B3 -> -649.2 | C13: =-CUPONI!C2+CUPONI!C3 -> -428.4 | D13: =-CUPONI!D2+CUPONI!D3 -> -208.8 | F13: =-CUPONI!F2+CUPONI!F3 -> -678 | G13: =-CUPONI!G2+CUPONI!G3 -> -678 | H13: =-CUPONI!H2+CUPONI!H3 -> -678 | I13: =-CUPONI!I2+CUPONI!I3 -> -288 | J13: =-CUPONI!J2+CUPONI!J3 -> -288 | K13: =-CUPONI!K2+CUPONI!K3 -> -288 | L13: =-CUPONI!L2+CUPONI!L3 -> -288 | M13: =-CUPONI!M2+CUPONI!M3 -> -288 | N13: =-CUPONI!N2+CUPONI!N3 -> 0 | Q13: =SUM(B13:O13) -> -4760.4
A14: =A5 -> MANIPULAE | C14: =-MANI!C2+MANI!C6 -> -2386.56 | D14: =-MANI!D2+MANI!D6 -> -2976.384 | E14: =-MANI!E2+MANI!E6 -> -6080 | F14: =-MANI!F2+MANI!F6 -> -7122.432 | G14: =-MANI!G2+MANI!G6 -> -4408.32 | H14: =-MANI!H2+MANI!H6 -> -2795.52 | I14: =-MANI!I2+MANI!I6 -> -2795.52 | J14: =-MANI!J2+MANI!J6 -> -1182.72 | ... N14: =-MANI!N2+MANI!N6 -> 0 | Q14: =SUM(B14:O14) -> -29747.456
A15: =A6 -> ANBIMA - REUNE | E15: =('ANBIMA - REUNE'!E3-'ANBIMA - REUNE'!E2)+('ANBIMA - REUNE'!F3-'ANBIMA - REUNE'!F2) -> -10375.68 | F15: ='ANBIMA - REUNE'!F3-'ANBIMA - REUNE'!F2 -> -8711.04 | G15: ='ANBIMA - REUNE'!G3-'ANBIMA - REUNE'!G2 -> -23466.24 | H15: ='ANBIMA - REUNE'!H3-'ANBIMA - REUNE'!H2 -> -23466.24 | I15: ='ANBIMA - REUNE'!I3-'ANBIMA - REUNE'!I2 -> -21288.96 | J15: ='ANBIMA - REUNE'!J3-'ANBIMA - REUNE'!J2 -> -8588.16 | K15: ='ANBIMA - REUNE'!K3-'ANBIMA - REUNE'!K2 -> 0 | L15: =-('ANBIMA - REUNE'!L2)+('ANBIMA - REUNE'!L3) -> 0 | M15: =-('ANBIMA - REUNE'!M2)+('ANBIMA - REUNE'!M3) -> 0 | N15: =-('ANBIMA - REUNE'!N2)+('ANBIMA - REUNE'!N3) -> 0 | Q15: =SUM(B15:O15) -> -95896.32
A16: =A7 -> ANBIMA - SAIDA DE DADOS | G16: ='ANBIMA - Saida de Dados'!F3-'ANBIMA - Saida de Dados'!F2 -> 0 | H16: ='ANBIMA - Saida de Dados'!G3-'ANBIMA - Saida de Dados'!G2 -> -4980 | I16: ='ANBIMA - Saida de Dados'!H3-'ANBIMA - Saida de Dados'!H2 -> -25496 | J16: ='ANBIMA - Saida de Dados'!I3-'ANBIMA - Saida de Dados'!I2 -> -66240 | K16: ='ANBIMA - Saida de Dados'!J3-'ANBIMA - Saida de Dados'!J2 -> -64080 | L16: ='ANBIMA - Saida de Dados'!K3-'ANBIMA - Saida de Dados'!K2 -> -75600 | M16: ='ANBIMA - Saida de Dados'!L3-'ANBIMA - Saida de Dados'!L2 -> -68400 | N16: ='ANBIMA - Saida de Dados'!M3-'ANBIMA - Saida de Dados'!M2 -> -72000 | Q16: =SUM(B16:O16) -> -376796
A17: =A8 -> CREFISA | G17: =(CREFISA!E3-CREFISA!E2)+(CREFISA!F3-CREFISA!F2) -> -6257.664 | H17: =CREFISA!G3-CREFISA!G2 -> -8070.4 | I17: =CREFISA!H3-CREFISA!H2 -> -7822.08 | J17: =CREFISA!I3-CREFISA!I2 -> -14079.744 | K17: =CREFISA!J3-CREFISA!J2 -> -14079.744 | L17: =CREFISA!K3-CREFISA!K2 -> -14079.744 | M17: =CREFISA!L3-CREFISA!L2 -> -14079.744 | N17: =CREFISA!M3-CREFISA!M2 -> -14079.744 | Q17: =SUM(B17:O17) -> -92548.864
A18: =A9 -> PIQCOIN | Q18: =SUM(B18:O18) -> 0
A19: =A10 -> COGNA - KEEGGO | G19: ='COGNA - KEEGGO'!F3-'COGNA - KEEGGO'!F2 -> -3024 | H19: ='COGNA - KEEGGO'!G3-'COGNA - KEEGGO'!G2 -> -4032 | Q19: =SUM(B19:O19) -> -7056
A20: =A11 -> LPs | E20: =-LPs!D2*8% -> -2472 | F20: =-LPs!E2*8% -> -200 | G20: =-LPs!F2*8% -> -200 | H20: =-LPs!G2*8% -> 0 | I20: =-LPs!G2+LPs!G9 -> 0 | J20: =-LPs!H2+LPs!H9 -> 0 | K20: =-LPs!I2+LPs!I9 -> 0 | L20: =-LPs!J2+LPs!J9 -> 0 | M20: =-LPs!K2+LPs!K9 -> 0 | Q20: =SUM(B20:O20) -> -2872
A21: RECEITA LÍQUIDA | B21: =B12 -> -1192.71 | C21: =C3+C12 -> 11718.86 | D21: =D3+D12 -> 49946.8 | E21: =E3+E12 -> 62031.44 | F21: =F3+F12 -> 107194.82 | G21: =G3+G12 -> 354985.12 | H21: =H3+H12 -> 313664.53 | I21: =I3+I12 -> 312018.58 | J21: =J3+J12 -> 428178.64 | ... O21: =O3+O12 -> 250032.26 | Q21: =SUM(B21:O21) -> 3216352.9 | T21: 106900
T22: -8551.73
A23: (=) CUSTO TOTAL | B23: =B25+B34+B40+B67 -> -15709.81 | C23: =C25+C34+C40+C67 -> -18645.71 | D23: =D25+D34+D40+D67 -> -20591.02 | E23: =E25+E34+E40+E67 -> -20436.27 | F23: =F25+F34+F40+F67 -> -101826.81 | G23: =G25+G34+G40+G67 -> -127044.13 | H23: =H25+H34+H40+H67 -> -177968.44 | I23: =I25+I34+I40+I67 -> -245691.18 | ... N23: =N25+N34+N40+N67 -> -215550 | Q23: =SUM(B23:O23) -> -1931121.5 | T23: =T22/T21 -> -0.079997474
T24: =T22+E15 -> -18927.41
A25: (=) CUSTO PROJETOS | B25: =SUM(B26:B33) -> -13000 | C25: =SUM(C26:C33) -> -13220 | D25: =SUM(D26:D33) -> -14036 | E25: =SUM(E26:E33) -> -9784 | F25: =SUM(F26:F33) -> -77941 | G25: =SUM(G26:G33) -> -89929 | H25: =SUM(H26:H33) -> -124642.86 | I25: =SUM(I26:I33) -> -195800 | ... N25: =SUM(N26:N33) -> -198300 | Q25: =SUM(B25:O25) -> -1519663.4
A26: =A4 -> CUPONI | B26: ='RESUMO PROJETOS'!B12 -> -13000 | C26: ='RESUMO PROJETOS'!C12 -> -13220 | D26: ='RESUMO PROJETOS'!D12 -> -11036 | E26: ='RESUMO PROJETOS'!E12 -> -1184 | F26: ='RESUMO PROJETOS'!F12 -> -1560 | G26: ='RESUMO PROJETOS'!G12 -> -9300 | H26: ='RESUMO PROJETOS'!H12 -> -9300 | I26: ='RESUMO PROJETOS'!I12 -> -9300 | ... N26: ='RESUMO PROJETOS'!N12 -> -2800
A27: =A5 -> MANIPULAE | B27: ='RESUMO PROJETOS'!B13 -> 0 | C27: ='RESUMO PROJETOS'!C13 -> 0 | D27: ='RESUMO PROJETOS'!D13 -> -3000 | E27: ='RESUMO PROJETOS'!E13 -> -3000 | F27: ='RESUMO PROJETOS'!F13 -> -22000 | G27: ='RESUMO PROJETOS'!G13 -> -22000 | H27: ='RESUMO PROJETOS'!H13 -> -7500 | I27: ='RESUMO PROJETOS'!I13 -> 0 | ... N27: ='RESUMO PROJETOS'!N13 -> 0
A28: =A6 -> ANBIMA - REUNE | B28: ='RESUMO PROJETOS'!B14 -> 0 | C28: ='RESUMO PROJETOS'!C14 -> 0 | D28: ='RESUMO PROJETOS'!D14 -> 0 | E28: ='RESUMO PROJETOS'!E14 -> 0 | F28: ='RESUMO PROJETOS'!F14 -> -34000 | G28: ='RESUMO PROJETOS'!G14 -> -34000 | H28: ='RESUMO PROJETOS'!H14 -> -44000 | I28: ='RESUMO PROJETOS'!I14 -> -32000 | ... N28: ='RESUMO PROJETOS'!N14 -> 0
A29: =A7 -> ANBIMA - SAIDA DE DADOS | H29: ='ANBIMA - Saida de Dados'!H8 -> -20928.576 | I29: ='ANBIMA - Saida de Dados'!I8 -> -124500 | J29: ='ANBIMA - Saida de Dados'!J8 -> -144500 | K29: ='ANBIMA - Saida de Dados'!K8 -> -155214.29 | L29: ='ANBIMA - Saida de Dados'!L8 -> -169500 | M29: ='ANBIMA - Saida de Dados'!M8 -> -169500 | N29: ='ANBIMA - Saida de Dados'!N8 -> -169500
A30: =A8 -> CREFISA | B30: ='RESUMO PROJETOS'!B16 -> 0 | C30: ='RESUMO PROJETOS'!C16 -> 0 | D30: ='RESUMO PROJETOS'!D16 -> 0 | E30: ='RESUMO PROJETOS'!E16 -> -3100 | F30: ='RESUMO PROJETOS'!F16 -> -19381 | G30: ='RESUMO PROJETOS'!G16 -> -23429 | H30: ='RESUMO PROJETOS'!H16 -> -26714.286 | I30: ='RESUMO PROJETOS'!I16 -> -30000 | ... N30: ='RESUMO PROJETOS'!N16 -> -26000
A31: =A19 -> COGNA - KEEGGO | G31: ='RESUMO PROJETOS'!F17 -> 0 | H31: ='RESUMO PROJETOS'!G17 -> -15000
A32: LPs | B32: ='RESUMO PROJETOS'!B18 -> 0 | C32: ='RESUMO PROJETOS'!C18 -> 0 | D32: ='RESUMO PROJETOS'!D18 -> 0 | E32: ='RESUMO PROJETOS'!E18 -> -2500 | F32: ='RESUMO PROJETOS'!F18 -> -1000 | G32: ='RESUMO PROJETOS'!G18 -> -1200 | H32: ='RESUMO PROJETOS'!H18 -> -1200 | I32: ='RESUMO PROJETOS'!I18 -> 0 | ... N32: ='RESUMO PROJETOS'!N18 -> 0
A34: (=) CUSTO PESSOAS DESALOCADAS | B34: =SUM(B35:B39) -> -1200 | C34: =SUM(C35:C39) -> -1200 | D34: =SUM(D35:D39) -> -1200 | E34: =SUM(E35:E39) -> -1200 | F34: =SUM(F35:F39) -> -1200 | G34: =SUM(G35:G39) -> -343 | H34: =SUM(H35:H39) -> -10050 | I34: =SUM(I35:I39) -> -14250 | ... N34: =SUM(N35:N39) -> -17250 | Q34: =SUM(B34:O34) -> -110893
A35: Rafael Panhoca | B35: =-VLOOKUP($A$35,'ZH02'!$B:$N,4,0) -> -1200 | C35: =-VLOOKUP($A$35,'ZH02'!$B:$N,4,0) -> -1200 | D35: =-VLOOKUP($A$35,'ZH02'!$B:$N,4,0) -> -1200 | E35: =-VLOOKUP($A$35,'ZH02'!$B:$N,4,0) -> -1200 | F35: =-VLOOKUP($A$35,'ZH02'!$B:$N,4,0) -> -1200 | I35: =-VLOOKUP($A$35,'ZH02'!$B:$N,4,0) -> -1200 | J35: =-VLOOKUP($A$35,'ZH02'!$B:$N,4,0) -> -1200 | K35: =-VLOOKUP($A$35,'ZH02'!$B:$N,4,0) -> -1200 | L35: =-VLOOKUP($A$35,'ZH02'!$B:$N,4,0) -> -1200 | M35: =-VLOOKUP($A$35,'ZH02'!$B:$N,4,0) -> -1200 | N35: =-VLOOKUP($A$35,'ZH02'!$B:$N,4,0) -> -1200
A36: Fernando | G36: -343 | H36: =-VLOOKUP($A$35,'ZH02'!$B:$N,4,0) -> -1200 | I36: =-VLOOKUP($A$35,'ZH02'!$B:$N,4,0) -> -1200 | J36: =-VLOOKUP($A$35,'ZH02'!$B:$N,4,0) -> -1200 | K36: =-VLOOKUP($A$35,'ZH02'!$B:$N,4,0) -> -1200 | L36: =-VLOOKUP($A$35,'ZH02'!$B:$N,4,0) -> -1200 | M36: =-VLOOKUP($A$35,'ZH02'!$B:$N,4,0) -> -1200 | N36: =-VLOOKUP($A$35,'ZH02'!$B:$N,4,0) -> -1200
A37: Amanda | L37: =-VLOOKUP($A$37,'ZH02'!$B:$N,4,0) -> -3000 | M37: =-VLOOKUP($A$37,'ZH02'!$B:$N,4,0) -> -3000 | N37: =-VLOOKUP($A$37,'ZH02'!$B:$N,4,0) -> -3000
A38: Alice Almeida | H38: =-VLOOKUP($A$38,'ZH02'!$B:$N,4,0) -> -8850 | I38: =-VLOOKUP($A$38,'ZH02'!$B:$N,4,0) -> -8850 | J38: =-VLOOKUP($A$38,'ZH02'!$B:$N,4,0) -> -8850 | K38: =-VLOOKUP($A$38,'ZH02'!$B:$N,4,0) -> -8850 | L38: =-VLOOKUP($A$38,'ZH02'!$B:$N,4,0) -> -8850 | M38: =-VLOOKUP($A$38,'ZH02'!$B:$N,4,0) -> -8850 | N38: =-VLOOKUP($A$38,'ZH02'!$B:$N,4,0) -> -8850
A39: Raphaela Oliveira | I39: =-VLOOKUP($A$39,'ZH02'!$B:$N,4,0) -> -3000 | J39: =-VLOOKUP($A$39,'ZH02'!$B:$N,4,0) -> -3000 | K39: =-VLOOKUP($A$39,'ZH02'!$B:$N,4,0) -> -3000 | L39: =-VLOOKUP($A$39,'ZH02'!$B:$N,4,0) -> -3000 | M39: =-VLOOKUP($A$39,'ZH02'!$B:$N,4,0) -> -3000 | N39: =-VLOOKUP($A$39,'ZH02'!$B:$N,4,0) -> -3000
A40: (=) CUSTO OPERACIONAL | B40: =SUM(B41:B66) -> -1509.81 | C40: =SUM(C41:C66) -> -1699.81 | D40: =SUM(D41:D66) -> -2092.79 | E40: =SUM(E41:E66) -> -2275.33 | F40: =SUM(F41:F66) -> -7965.33 | G40: =SUM(G41:G66) -> -14460.4 | H40: =SUM(H41:H66) -> -16878.75 | I40: =SUM(I41:I66) -> -16878.75 | ... N40: =SUM(N41:N66) -> 0 | Q40: =SUM(B40:O40) -> -133791.47
A41: TFE - Prefeitura Orla Tech | G41: -236.98
A42: TFE - Prefeitura Orla Digital | G42: -206.68
A43: Mudança societaria | G43: -1700
A44: Abertura Empresa Orla Tech | C44: -400 | D44: -269.9
A45: INSS | B45: -148.5 | C45: -148.5 | D45: -148.5 | E45: -445.5 | F45: -445.5 | G45: -445.5 | H45: -445.5 | I45: -445.5 | J45: -445.5 | K45: -445.5 | L45: -445.5 | M45: -445.5
A46: Plano de Saúde | H46: -4120.76 | I46: -4120.76 | J46: -4120.76 | K46: -4120.76 | L46: -4120.76 | M46: -4120.76
A47: Manutenção Ar condicionado | G47: -157.75 | J47: -157.75 | M47: -157.75
A48: Clicksign | E48: -60 | F48: -59.5 | G48: =-39-51 -> -90 | H48: -39 | I48: -39 | J48: -39 | K48: -39 | L48: -39 | M48: -39
A49: Celular Gustavo | F49: -400 | G49: -400 | H49: -400 | I49: -400 | J49: -400 | K49: -400 | L49: -400 | M49: -400
A50: Escritorio | G50: -300 | H50: -600 | I50: -600 | J50: -600 | K50: -600 | L50: -600 | M50: -600
A51: Internet
A52: ifood para o time (15) | G52: -750
A53: Advogado | G53: -2100 | H53: -2100 | I53: -2100 | J53: -2100 | K53: -2100 | L53: -2100 | M53: -2100
A54: Contador | B54: -450 | C54: -240 | D54: -480 | E54: -900 | F54: -900 | G54: -900 | H54: -2000 | I54: -2000 | J54: -2000 | K54: -2000 | L54: -2000 | M54: -2000
A55: Dominio valido po 1 ano | D55: -280.65
A56: Figma Licença anual | F56: -1521.48
A57: Slack | F57: -600 | G57: -600 | H57: -600 | I57: -600 | J57: -600 | K57: -600 | L57: -600 | M57: -600
A58: Gsuite | B58: -170.1 | C58: -170.1 | D58: -170.1 | E58: -176.18 | F58: -364.5 | G58: -364.5 | H58: -364.5 | I58: -364.5 | J58: -364.5 | K58: -364.5 | L58: -364.5 | M58: -364.5
A59: Monday/clickup | B59: -455 | C59: -455 | D59: -455 | E59: -378.71 | F59: -500 | G59: -850 | H59: -850 | I59: -850 | J59: -1200 | K59: -1200 | L59: -1600 | M59: -1600
A60: Adobe | B60: -69 | C60: -69 | D60: -69 | E60: -69 | F60: -69 | G60: -69 | H60: -69 | I60: -69 | J60: -69 | K60: -69 | L60: -69 | M60: -69
A61: Hostinger | B61: -29.99 | C61: -29.99 | D61: -29.99 | E61: -29.99 | F61: -29.99 | G61: -29.99 | H61: -29.99 | I61: -29.99 | J61: -29.99 | K61: -29.99 | L61: -29.99 | M61: -29.99
A62: Elementor | F62: -315.36
A63: Webflow | B63: -97.22 | C63: -97.22 | D63: -99.65 | E63: -95.38 | F63: -170 | G63: -170 | H63: -170 | I63: -170 | J63: -170 | K63: -170 | L63: -170 | M63: -170
A64: AWS | E64: =-5.07-25.5 -> -30.57 | F64: -2500 | G64: -5000 | H64: -5000 | I64: -5000 | J64: -5000 | K64: -5000 | L64: -5000 | M64: -5000
A65: Suporte | B65: -90 | C65: -90 | D65: -90 | E65: -90 | F65: -90 | G65: -90 | H65: -90 | I65: -90 | J65: -90 | K65: -90 | L65: -90 | M65: -90
A67: (=) CUSTO REEMBOLSO | B67: =SUM(B68:B70) -> 0 | C67: =SUM(C68:C70) -> -2525.9 | D67: =SUM(D68:D70) -> -3262.23 | E67: =SUM(E68:E70) -> -7176.94 | F67: =SUM(F68:F70) -> -14720.48 | G67: =SUM(G68:G70) -> -22311.73 | H67: =SUM(H68:H70) -> -26396.83 | I67: =SUM(I68:I70) -> -18762.43 | ... O67: =SUM(O68:O70) -> 0 | Q67: =SUM(B67:O67) -> -166773.7
A68: (-) KAIQUE | B68: =REEMBOLSO!B58+REEMBOLSO!B23 -> 0 | C68: =REEMBOLSO!C58+REEMBOLSO!C23 -> 0 | D68: =REEMBOLSO!D58+REEMBOLSO!D23 -> 0 | E68: =REEMBOLSO!E58+REEMBOLSO!E23 -> -785.99 | F68: =REEMBOLSO!F58+REEMBOLSO!F23 -> -422 | G68: =REEMBOLSO!G58+REEMBOLSO!G23 -> -1537.23 | H68: =REEMBOLSO!H58+REEMBOLSO!H23 -> -3183 | I68: =REEMBOLSO!I58+REEMBOLSO!I23 -> -2210 | ... M68: =REEMBOLSO!M58+REEMBOLSO!M23 -> -2210 | Q68: =SUM(B68:O68) -> -16978.22
A69: (-) MOHAMAD | B69: =REEMBOLSO!B34+REEMBOLSO!B61 -> 0 | C69: =REEMBOLSO!C34+REEMBOLSO!C61 -> -2525.9 | D69: =REEMBOLSO!D34+REEMBOLSO!D61 -> -2668.23 | E69: =REEMBOLSO!E34+REEMBOLSO!E61 -> -5227.31 | F69: =REEMBOLSO!F34+REEMBOLSO!F61 -> -8905.48 | G69: =REEMBOLSO!G34+REEMBOLSO!G61 -> -10997.22 | H69: =REEMBOLSO!H34+REEMBOLSO!H61 -> -13868.78 | I69: =REEMBOLSO!I34+REEMBOLSO!I61 -> -12145.23 | ... M69: =REEMBOLSO!M34+REEMBOLSO!M61 -> -9062.27 | Q69: =SUM(B69:O69) -> -101836.11
A70: (-) SABA | B70: =REEMBOLSO!B52+REEMBOLSO!B3 -> 0 | C70: =REEMBOLSO!C52+REEMBOLSO!C3 -> 0 | D70: =REEMBOLSO!D52+REEMBOLSO!D3 -> -594 | E70: =REEMBOLSO!E52+REEMBOLSO!E3 -> -1163.64 | F70: =REEMBOLSO!F52+REEMBOLSO!F3 -> -5393 | G70: =REEMBOLSO!G52+REEMBOLSO!G3 -> -9777.28 | H70: =REEMBOLSO!H52+REEMBOLSO!H3 -> -9345.05 | I70: =REEMBOLSO!I52+REEMBOLSO!I3 -> -4407.2 | ... M70: =REEMBOLSO!M52+REEMBOLSO!M3 -> -4232.4 | Q70: =SUM(B70:O70) -> -47959.37
A72: (=) PRO-LABORE | B72: =SUM(B73:B75) -> -10000 | C72: =SUM(C73:C75) -> 0 | D72: =SUM(D73:D75) -> 245 | E72: =SUM(E73:E75) -> 0 | F72: =SUM(F73:F75) -> 0 | G72: =SUM(G73:G75) -> -48208.28 | H72: =SUM(H73:H75) -> -46747.23 | I72: =SUM(I73:I75) -> -46747.23 | ... M72: =SUM(M73:M75) -> -58747.23
A73: =A68 -> (-) KAIQUE | B73: -10000 | D73: -10000 | G73: =-13000-1992.26-(1035.5*2) -> -17063.26 | H73: -16000 | I73: -16000 | J73: -16000 | K73: -20000 | L73: -20000 | M73: -20000
A74: =A69 -> (-) MOHAMAD | G74: =-13000-1992.26-125 -> -15117.26 | H74: -16000 | I74: -16000 | J74: -16000 | K74: -20000 | L74: -20000 | M74: -20000
A75: =A70 -> (-) SABA | D75: 10245 | G75: =-13000-1992.26-1035.5 -> -16027.76 | H75: =-16000+1252.77 -> -14747.23 | I75: =-16000+1252.77 -> -14747.23 | J75: =-16000+1252.77 -> -14747.23 | K75: =-20000+1252.77 -> -18747.23 | L75: =-20000+1252.77 -> -18747.23 | M75: =-20000+1252.77 -> -18747.23
A77: (=) LUCRO LÍQUIDO | B77: =B21+B23+B72 -> -26902.52 | C77: =C21+C23+C72 -> -6926.85 | D77: =D21+D23+D72 -> 29600.78 | E77: =E21+E23+E72 -> 41595.17 | F77: =F21+F23+F72 -> 5368.006 | G77: =G21+G23+G72 -> 179732.71 | H77: =H21+H23+H72 -> 88948.857 | I77: =I21+I23+I72 -> 19580.166 | ... O77: =O21+O23+O72 -> 250032.26 | Q77: =SUM(B77:O77) -> 910784.65 | R77: =Q77/Q21 -> 0.28317311 | T77: 1006563.7
A78: SALDO BANCARIO PROJEÇÃO | D78: =D77 -> 29600.78 | E78: =D78+E77 -> 71195.95 | F78: =E78+F77 -> 76563.956 | G78: =F78+G77 -> 256296.67 | H78: =G78+H77 -> 345245.52 | I78: =H78+I77 -> 364825.69 | J78: =I78+J77 -> 505461.94 | K78: =J78+K77 -> 598045.48 | L78: =K78+L77 -> 568094.05 | ... O78: =N78+O77 -> 944614.02 | T78: =Q77-T77 -> -95779.003
A80: RESERVAS | B80: =SUM(B81:B82) -> 0 | C80: =SUM(C81:C82) -> 0 | D80: =SUM(D81:D82) -> 0 | E80: =SUM(E81:E82) -> 0 | F80: =SUM(F81:F82) -> 0 | G80: =SUM(G81:G82) -> 0 | H80: =SUM(H81:H82) -> 0 | I80: =SUM(I81:I82) -> 0 | ... O80: =SUM(O81:O82) -> 0 | Q80: =SUM(B80:O80) -> -271759.4 | T80: =7000*12 -> 84000
A81: RECESSO | M81: =(Q25+Q34)/12 -> -135879.7 | Q81: =SUM(B81:O81) -> -135879.7
A82: BONUS | M82: =(Q25+Q34)/12 -> -135879.7 | Q82: =SUM(B82:O82) -> -135879.7
A84: (=) LUCRO LÍQUIDO - RESERVAS | B84: =B77-B80 -> -26902.52 | C84: =C77-C80 -> -6926.85 | D84: =D77-D80 -> 29600.78 | E84: =E77-E80 -> 41595.17 | F84: =F77-F80 -> 5368.006 | G84: =G77-G80 -> 179732.71 | H84: =H77-H80 -> 88948.857 | I84: =I77-I80 -> 19580.166 | ... O84: =O77-O80 -> 250032.26 | Q84: =Q77+Q80 -> 639025.25 | R84: =Q84/Q21 -> 0.19868008
A86: INVESTIMENTO SÓCIOS | B86: =SUM(B87:B89) -> 3600 | C86: =SUM(C87:C89) -> 5100 | D86: =SUM(D87:D89) -> 30000 | E86: =SUM(E87:E89) -> 39000 | F86: =SUM(F87:F89) -> 45000 | G86: =SUM(G87:G89) -> 0 | H86: =SUM(H87:H89) -> 0 | I86: =SUM(I87:I89) -> 0 | ... O86: =SUM(O87:O89) -> 0 | Q86: =SUM(B86:O86) -> 122700
A87: Kaique | B87: 1200 | C87: 1700 | D87: 10000 | E87: 13000 | F87: 15000 | Q87: =SUM(B87:M87) -> 40900
A88: Mohamad | B88: 1200 | C88: 1700 | D88: 10000 | E88: 13000 | F88: 15000 | Q88: =SUM(B88:M88) -> 40900
A89: Saba | B89: 1200 | C89: 1700 | D89: 10000 | E89: 13000 | F89: 15000 | Q89: =SUM(B89:M89) -> 40900
A91: (=) LUCRO LÍQUIDO - RESERVAS - INVESTIMENTO | B91: =B84-B86 -> -30502.52 | C91: =C84-C86 -> -12026.85 | D91: =D84-D86 -> -399.22 | E91: =E84-E86 -> 2595.17 | F91: =F84-F86 -> -39631.994 | G91: =G84-G86 -> 179732.71 | H91: =H84-H86 -> 88948.857 | I91: =I84-I86 -> 19580.166 | ... O91: =O84-O86 -> 250032.26 | Q91: =Q84-Q86 -> 516325.25 | R91: =Q91/Q21 -> 0.16053128
Q95: =Q91*5% -> 25816.263

Sheet Sheet1
G2: =168 -> 168
H4: mês 1 | I4: mês 2 | J4: mês 3 | K4: mês 4 | L4: mês 5 | M4: mês 6 | N4: mês 7
F5: Gestão | H5: 0.2 | I5: 0.2 | J5: 0.2 | K5: 0.2 | L5: 0.2 | M5: 0.2
F6: PM | H6: 1 | I6: 1 | J6: 1 | K6: 1 | L6: 1 | M6: 1 | N6: 0.5
F7: Designer | H7: 1 | I7: 1 | J7: 1 | K7: 1 | L7: 1 | M7: 1
F8: Dev | H8: 1 | I8: 1 | J8: 1 | K8: 1 | L8: 1 | M8: 1
F9: Dev | H9: 1 | I9: 1 | J9: 1 | K9: 1 | L9: 1 | M9: 1 | P9: =SUM(N5:N12)*G2 -> 420
F10: Dev | I10: 1 | J10: 1 | K10: 1 | L10: 1 | M10: 1 | N10: 1
F11: Dev | I11: 1 | J11: 1 | K11: 1 | L11: 1 | M11: 1 | N11: 1
F12: QA | I12: 1 | J12: 1 | K12: 1 | L12: 1 | M12: 1 | P12: =SUM(H5:M12)*G2 -> 6753.6
H14: mês 1 | I14: mês 2 | J14: mês 3 | K14: mês 4 | L14: mês 5 | M14: mês 6 | N14: mês 7
F15: =F5 -> Gestão | G15: 320
F16: =F6 -> PM | G16: 200 | H16: =H6*$G16*$G$2 -> 33600 | I16: =I6*$G16*$G$2 -> 33600 | J16: =J6*$G16*$G$2 -> 33600 | K16: =K6*$G16*$G$2 -> 33600 | L16: =L6*$G16*$G$2 -> 33600 | M16: =M6*$G16*$G$2 -> 33600 | N16: =N6*$G16*$G$2 -> 16800
F17: =F7 -> Designer | G17: 180 | H17: =H7*$G17*$G$2 -> 30240 | I17: =I7*$G17*$G$2 -> 30240 | J17: =J7*$G17*$G$2 -> 30240 | K17: =K7*$G17*$G$2 -> 30240 | L17: =L7*$G17*$G$2 -> 30240 | M17: =M7*$G17*$G$2 -> 30240 | N17: =N7*$G17*$G$2 -> 0
F18: =F8 -> Dev | G18: 180 | H18: =H8*$G18*$G$2 -> 30240 | I18: =I8*$G18*$G$2 -> 30240 | J18: =J8*$G18*$G$2 -> 30240 | K18: =K8*$G18*$G$2 -> 30240 | L18: =L8*$G18*$G$2 -> 30240 | M18: =M8*$G18*$G$2 -> 30240 | N18: =N8*$G18*$G$2 -> 0
F19: =F9 -> Dev | G19: 180 | H19: =H9*$G19*$G$2 -> 30240 | I19: =I9*$G19*$G$2 -> 30240 | J19: =J9*$G19*$G$2 -> 30240 | K19: =K9*$G19*$G$2 -> 30240 | L19: =L9*$G19*$G$2 -> 30240 | M19: =M9*$G19*$G$2 -> 30240 | N19: =N9*$G19*$G$2 -> 0 | P19: =SUM(H15:M22) -> 1132320 | Q19: =P19/P12 -> 167.66169
F20: =F10 -> Dev | G20: 160 | H20: =H10*$G20*$G$2 -> 0 | I20: =I10*$G20*$G$2 -> 26880 | J20: =J10*$G20*$G$2 -> 26880 | K20: =K10*$G20*$G$2 -> 26880 | L20: =L10*$G20*$G$2 -> 26880 | M20: =M10*$G20*$G$2 -> 26880 | N20: =N10*$G20*$G$2 -> 26880 | P20: =P19-H24 -> 1008000
F21: =F11 -> Dev | G21: 140 | H21: =H11*$G21*$G$2 -> 0 | I21: =I11*$G21*$G$2 -> 23520 | J21: =J11*$G21*$G$2 -> 23520 | K21: =K11*$G21*$G$2 -> 23520 | L21: =L11*$G21*$G$2 -> 23520 | M21: =M11*$G21*$G$2 -> 23520 | N21: =N11*$G21*$G$2 -> 23520 | P21: 1178352
F22: =F12 -> QA | G22: 160 | H22: =H12*$G22*$G$2 -> 0 | I22: =I12*$G22*$G$2 -> 26880 | J22: =J12*$G22*$G$2 -> 26880 | K22: =K12*$G22*$G$2 -> 26880 | L22: =L12*$G22*$G$2 -> 26880 | M22: =M12*$G22*$G$2 -> 26880 | N22: =N12*$G22*$G$2 -> 0
H24: =SUM(H15:H22) -> 124320 | I24: =SUM(I15:I22) -> 201600 | J24: =SUM(J15:J22) -> 201600 | K24: =SUM(K15:K22) -> 201600 | L24: =SUM(L15:L22) -> 201600 | M24: =SUM(M15:M22) -> 201600 | N24: =SUM(N15:N22) -> 67200

Sheet REEMBOLSO
A1: Orla REEMBOLSO | B1: 44927 | C1: 44958 | D1: 44986 | E1: 45017 | F1: 45047 | G1: 45078 | H1: 45108 | I1: 45139 | J1: 45170 | K1: 45200 | L1: 45231 | M1: 45261
B2: R$ | C2: R$ | D2: R$ | E2: R$ | F2: R$ | G2: R$ | H2: R$ | I2: R$ | J2: R$ | K2: R$ | L2: R$ | M2: R$
A3: REEMBOLSO SABA | B3: =SUM(B4:B22) -> 0 | C3: =SUM(C4:C22) -> 0 | D3: =SUM(D4:D22) -> -594 | E3: =SUM(E4:E22) -> -1163.64 | F3: =SUM(F4:F22) -> -2353 | G3: =SUM(G4:G22) -> -6506.78 | H3: =SUM(H4:H22) -> -6077.85 | I3: =SUM(I4:I22) -> -1140 | ... M3: =SUM(M4:M22) -> -1140
A4: Almoço Crefisa | D4: -214
A5: Café/Almoço Roma | E5: =-94.13-60 -> -154.13 | G5: =-580.82-30 -> -610.82 | P5: Passagem Arthur/Allan - 3/10 | Q5: 147.36
A6: Febraban | H6: -2650 | P6: Divino Fogão | Q6: 50.23
A7: estacionamento Febraban | H7: =-65*3 -> -195 | P7: Pecorino | Q7: 74.2
A8: Almoço Febraban | H8: =-85*4 -> -340 | P8: Hubees | Q8: 55.99
A9: Café Keego | E9: =-55-25 -> -80 | G9: =-700.6-23.01 -> -723.61 | P9: Divino Fogão | Q9: 56.33
A10: Café Crefisa | F10: -120 | H10: =-22.9*3 -> -68.7 | P10: Hubees | Q10: 55.99
A11: Estacionamento crefisa | E11: =-70-40 -> -110 | F11: -200 | G11: =-240-37 -> -277 | H11: -180 | I11: -240 | J11: -240 | K11: -240 | L11: -240 | M11: -240 | P11: Restaurante | Q11: 70.4
A12: Plugs notebooks | F12: =-110-98 -> -208 | P12: Hubees | Q12: 55.99
A13: Açai | F13: -155 | H13: -163 | P13: Hubees | Q13: 55.99
A14: Alimentação crefisa | F14: -900 | H14: =-314.6-400 -> -714.6 | I14: -900 | J14: -900 | K14: -900 | L14: -900 | M14: -900 | P14: Divino Fogão | Q14: 57.2
A15: Almoço Zmes | E15: =-480-40 -> -520 | P15: Netpark | Q15: 119.65
A16: Almoço funcionarios | F16: =-220-120-80-130-110 -> -660 | G16: =-140-123-281-139.9-294.12-122.8-280.54-122.97-139.22-84.58-139.6 -> -1867.73 | H16: =-123.6-374.49-33-41.9 -> -572.99 | P16: Computador 1 - 1/10 | Q16: 1550
A17: Jantar Crefisa | G17: =-173*2-30 -> -376 | P17: Computador 2 - 1/10 | Q17: 660
A18: Almoço Anbima | D18: -380 | E18: =-128.03-14.5-34.98-27 -> -204.51 | G18: =-283.63-30-446.4-51.17 -> -811.2 | H18: =-450.6-74.2-345 -> -869.8 | P18: Assaí - Compras escritório | Q18: 173.67
A19: Estacionamento Anbima | D19: q | H19: -70 | P19: Total | Q19: =SUM(Q5:Q18) -> 3183
A20: Churrasco Rio | G20: =-900-632.61-242.82-64.99 -> -1840.42
A21: Almoço Ache digita | H21: -253.76
A22: Almoço Anbima Selic | E22: -95 | F22: -110
A23: REEMBOLSO KAIQUE | B23: =SUM(B24:B33) -> 0 | C23: =SUM(C24:C33) -> 0 | D23: =SUM(D24:D33) -> 0 | E23: =SUM(E24:E33) -> -785.99 | F23: =SUM(F24:F33) -> -422 | G23: =SUM(G24:G33) -> -1537.23 | H23: =SUM(H24:H33) -> -973 | I23: =SUM(I24:I33) -> 0 | ... M23: =SUM(M24:M33) -> 0
A24: Estacionamento | E24: =-40-40-55.99 -> -135.99
A25: Almoço Anbima | H25: -308.36
A26: Passagens
A27: Passagens Allan/Arthur | G27: -459.16 | H27: -147.36
A28: Estacionamento | G28: -111.98 | H28: -343.61
A29: Airbnb Allan/Arthur | G29: -624.24
A30: Restaurantes | G30: -341.85
A31: Açai | F31: -127
A32: Mateiral escritorio | F32: -295 | H32: -173.67
A33: Advogado | E33: -650
A34: REEMBOLSO MOHAMAD | B34: =SUM(B35:B47) -> 0 | C34: =SUM(C35:C47) -> 0 | D34: =SUM(D35:D47) -> -142.33 | E34: =SUM(E35:E47) -> -1076.61 | F34: =SUM(F35:F47) -> -1162.04 | G34: =SUM(G35:G47) -> -796.32 | H34: =SUM(H35:H47) -> -1186.05 | I34: =SUM(I35:I47) -> 0 | ... M34: =SUM(M35:M47) -> 0
A35: Almoço/cafe mani | D35: -32.7 | E35: =-39.14-43.89-48.16 -> -131.19 | F35: -36.75
A36: Almoço Alice | F36: -291.28
A37: Uber Mani | D37: -56.63 | E37: =-46.16-34.65 -> -80.81 | F37: -40.76 | H37: -248.3
A38: Estacionamento zmes | E38: -40
A39: Motoboy
A40: Itens Escritorio | E40: -36.62 | F40: -129.8
A41: Almoço Elgin | F41: -271.48
A42: Restaurantes | G42: -214.15 | H42: =-109.42-254.93 -> -364.35
A43: Café | G43: -13.75
A44: Churrasco Orla | H44: -401
A45: mercado | G45: -188.42 | H45: -87.4
A46: Limpeza | E46: -600 | F46: -300 | G46: -300
A47: Estacionamento | D47: =-34-19 -> -53 | E47: =-30-34-34-34-55.99 -> -187.99 | F47: -91.97 | G47: =-30-50 -> -80 | H47: -85
A48: TOTAL | B48: =B3+B23+B34 -> 0 | C48: =C3+C23+C34 -> 0 | D48: =D3+D23+D34 -> -736.33 | E48: =E3+E23+E34 -> -3026.24 | F48: =F3+F23+F34 -> -3937.04 | G48: =G3+G23+G34 -> -8840.33 | H48: =H3+H23+H34 -> -8236.9 | I48: =I3+I23+I34 -> -1140 | ... M48: =M3+M23+M34 -> -1140
A50: Orla REEMBOLSO PC | B50: 44927 | C50: 44958 | D50: 44986 | E50: 45017 | F50: 45047 | G50: 45078 | H50: 45108 | I50: 45139 | J50: 45170 | K50: 45200 | L50: 45231 | M50: 45261
B51: R$ | C51: R$ | D51: R$ | E51: R$ | F51: R$ | G51: R$ | H51: R$ | I51: R$ | J51: R$ | K51: R$ | L51: R$ | M51: R$
A52: REEMBOLSO SABA | B52: =SUM(B53:B57) -> 0 | C52: =SUM(C53:C57) -> 0 | D52: =SUM(D53:D57) -> 0 | E52: =SUM(E53:E57) -> 0 | F52: =SUM(F53:F57) -> -3040 | G52: =SUM(G53:G57) -> -3270.5 | H52: =SUM(H53:H57) -> -3267.2 | I52: =SUM(I53:I57) -> -3267.2 | ... M52: =SUM(M53:M57) -> -3092.4
A53: PC Ericsson (10x) | F53: -1520 | G53: -1520 | H53: -1520 | I53: -1520 | J53: -1520 | K53: -1520 | L53: -1520 | M53: -1520
A54: Cadeira Escritorio (10x) | G54: -174.8 | H54: -174.8 | I54: -174.8 | J54: -174.8 | K54: -174.8
A55: Fechadura (8x) | H55: -52.4 | I55: -52.4 | J55: -52.4 | K55: -52.4 | L55: -52.4 | M55: -52.4
A56: estabilizador | G56: -55.7
A57: PC Gustavo (10x) | F57: -1520 | G57: -1520 | H57: -1520 | I57: -1520 | J57: -1520 | K57: -1520 | L57: -1520 | M57: -1520
A58: REEMBOLSO KAIQUE | B58: =SUM(B59:B59) -> 0 | C58: =SUM(C59:C59) -> 0 | D58: =SUM(D59:D59) -> 0 | E58: =SUM(E59:E59) -> 0 | F58: =SUM(F59:F59) -> 0 | G58: =SUM(G59:G59) -> 0 | H58: =SUM(H59:H60) -> -2210 | I58: =SUM(I59:I60) -> -2210 | J58: =SUM(J59:J60) -> -2210 | K58: =SUM(K59:K60) -> -2210 | L58: =SUM(L59:L60) -> -2210 | M58: =SUM(M59:M60) -> -2210
A59: PC Alexsandro (10x) | H59: -1550 | I59: -1550 | J59: -1550 | K59: -1550 | L59: -1550 | M59: -1550
A60: PC Jonatham (10x) | H60: -660 | I60: -660 | J60: -660 | K60: -660 | L60: -660 | M60: -660
A61: REEMBOLSO MOHAMAD | B61: =SUM(B62:B76) -> 0 | C61: =SUM(C62:C76) -> -2525.9 | D61: =SUM(D62:D76) -> -2525.9 | E61: =SUM(E62:E76) -> -4150.7 | F61: =SUM(F62:F76) -> -7743.44 | G61: =SUM(G62:G76) -> -10200.9 | H61: =SUM(H62:H76) -> -12682.73 | I61: =SUM(I62:I76) -> -12145.23 | ... M61: =SUM(M62:M76) -> -9062.27
A62: PC ALLAN (10x) | C62: =-1437 -> -1437 | D62: =-1437 -> -1437 | E62: =-1437 -> -1437 | F62: =-1437 -> -1437 | G62: =-1437 -> -1437 | H62: =-1437 -> -1437 | I62: =-1437 -> -1437 | J62: =-1437 -> -1437 | ... L62: =-1437 -> -1437
A63: PC ARTHUR (10x) | E63: -535.9 | F63: -535.9 | G63: -535.9 | H63: -535.9 | I63: -535.9 | J63: -535.9 | K63: -535.9 | L63: -535.9 | M63: -535.9
A64: Seguros (6x) | G64: -556.06 | H64: -556.06 | I64: -556.06 | J64: -556.06 | K64: -556.06 | L64: -556.06
A65: Pc Paiva (10x) | F65: -1481.94 | G65: -1481.94 | H65: -1481.94 | I65: -1481.94 | J65: -1481.94 | K65: -1481.94 | L65: -1481.94 | M65: -1481.94
A66: Cadeiras (3x) | F66: =-184.55*2 -> -369.1 | G66: =-184.55*2 -> -369.1 | H66: =-184.55*2 -> -369.1 | I66: =-184.55*2 -> -369.1 | J66: =-184.55*2 -> -369.1 | K66: =-184.55*2 -> -369.1 | L66: =-184.55*2 -> -369.1 | M66: =-184.55*2 -> -369.1
A67: Mesas (10x) | F67: -537.5 | G67: -537.5 | H67: -537.5
A68: PC Renata (10x) | H68: =-3399/10 -> -339.9 | I68: =-3399/10 -> -339.9 | J68: =-3399/10 -> -339.9 | K68: =-3399/10 -> -339.9 | L68: =-3399/10 -> -339.9 | M68: =-3399/10 -> -339.9
A69: PC Aline (10x) | H69: =-6460/10 -> -646 | I69: =-6460/10 -> -646 | J69: =-6460/10 -> -646 | K69: =-6460/10 -> -646 | L69: =-6460/10 -> -646 | M69: =-6460/10 -> -646
H70: -1495.93 | I70: -1495.93 | J70: -1495.93 | K70: -1495.93 | L70: -1495.93 | M70: -1495.93
A71: PC Mateus Chaves (10x) | G71: =-15500/10 -> -1550 | H71: =-15500/10 -> -1550 | I71: =-15500/10 -> -1550 | J71: =-15500/10 -> -1550 | K71: =-15500/10 -> -1550 | L71: =-15500/10 -> -1550 | M71: =-15500/10 -> -1550
A72: Pc Alice (10x) | G72: -351.4 | H72: -351.4 | I72: -351.4 | J72: -351.4 | K72: -351.4 | L72: -351.4 | M72: -351.4
A73: PC Gabi (10x) | F73: -646 | G73: -646 | H73: -646 | I73: -646 | J73: -646 | K73: -646 | L73: -646 | M73: -646
A74: PC Neto (10x) | F74: -646 | G74: -646 | H74: -646 | I74: -646 | J74: -646 | K74: -646 | L74: -646 | M74: -646
A75: PC AMANDA (10x) | E75: -1088.9 | F75: -1000.1 | G75: -1000.1 | H75: -1000.1 | I75: -1000.1 | J75: -1000.1 | K75: -1000.1 | L75: -1000.1 | M75: -1000.1
A76: PC RAPHA (10x) | C76: -1088.9 | D76: -1088.9 | E76: -1088.9 | F76: -1089.9 | G76: -1089.9 | H76: -1089.9 | I76: -1089.9 | J76: -1089.9 | K76: -1089.9 | L76: -1089.9
A77: TOTAL | B77: =B52+B58+B61 -> 0 | C77: =C52+C58+C61 -> -2525.9 | D77: =D52+D58+D61 -> -2525.9 | E77: =E52+E58+E61 -> -4150.7 | F77: =F52+F58+F61 -> -10783.44 | G77: =G52+G58+G61 -> -13471.4 | H77: =H52+H58+H61 -> -18159.93 | I77: =I52+I58+I61 -> -17622.43 | ... M77: =M52+M58+M61 -> -14364.67
A79: TOTAL GERAL | B79: =B48+B77 -> 0 | C79: =C48+C77 -> -2525.9 | D79: =D48+D77 -> -3262.23 | E79: =E48+E77 -> -7176.94 | F79: =F48+F77 -> -14720.48 | G79: =G48+G77 -> -22311.73 | H79: =H48+H77 -> -26396.83 | I79: =I48+I77 -> -18762.43 | ... M79: =M48+M77 -> -15504.67

Sheet Sheet2
A1: Pessoas | B1: Valor | C1: Data de pagamento | D1: Mês de competencia
A2: Advogado | B2: -2100 | C2: 45127 | D2: 45078
A3: Alteração da empresa | C3: 45127 | D3: 45078
A4: Braptech | B4: -90 | C4: 45127 | D4: 45078
A5: Contador Orla Digital | B5: -450 | C5: 45127 | D5: 45078
A6: Contador Orla Tech | B6: -450 | C6: 45127 | D6: 45078
A7: Gustavo Celular | B7: -400 | C7: 45127 | D7: 45078
A8: Imposto Orla Digital | B8: 30281.21 | C8: 45127 | D8: 45078
A9: Imposto Orla Tech | B9: -7905.97 | C9: 45127 | D9: 45078
A10: Inss Kaique | B10: -150 | C10: 45127 | D10: 45078
A11: Inss Moha | B11: -150 | C11: 45127 | D11: 45078
A12: Inss Saba | B12: -150 | C12: 45127 | D12: 45078
A13: Manutenção ar | B13: - | C13: 45127 | D13: 45078
A14: Neide | B14: -600 | C14: 45127 | D14: 45078
A15: Prolabore Kaique | B15: -16000 | C15: 45127 | D15: 45078
A16: Prolabore Moha | B16: -16000 | C16: 45127 | D16: 45078
A17: Prolabore Saba | B17: -16000 | C17: 45127 | D17: 45078
A18: Reembolso Amanda | C18: 45127 | D18: 45078

Sheet Pivot Pagamentos
A3: Sum of Valor | B3: Rótulos de Coluna
A4: Rótulos de Linha | B4: 44990 | C4: 45005 | D4: 44998 | E4: 45000 | F4: 44993 | G4: 45021 | H4: 45017 | I4: 45036 | J4: 45051 | K4: 45068 | L4: 45065 | M4: 45082 | N4: 45097 | O4: 45078 | P4: (vazio) | Q4: 45085 | R4: 45098 | S4: 45112 | T4: 45110 | U4: 45127 | V4: 45130 | W4: 45117 | X4: 45113 | Y4: Total Geral
A5: Adiantamento Erickson | U5: -3000 | Y5: -3000
A6: Adiantamento Mateus 2 | K6: -381 | Y6: -381
A7: Advogado | N7: -2100 | U7: -2100 | Y7: -4200
A8: Aleph | L8: 0 | Y8: 0
A9: Alexsandro Ramos | S9: -5714.29 | Y9: -5714.29
A10: Alice Almeida | S10: -8850 | Y10: -8850
A11: Aline Santos | S11: -7857.1429 | Y11: -7857.1429
A12: Allan | B12: -10000 | G12: -10000 | J12: -10000 | M12: -10000 | Y12: -40000
A13: Allan freela | N13: -780 | Y13: -780
A14: Allan Patrick De Freitas Santana | S14: -10000 | Y14: -10000
A15: Alteração da empresa | O15: -1700 | Y15: -1700
A16: Amanda | J16: -3000 | M16: -3000 | S16: -3000 | Y16: -9000
A17: Arthur | B17: -220 | G17: -1036 | J17: -13000 | M17: -13000 | S17: -13000 | Y17: -40256
A18: Arthur Freela | K18: -1184 | N18: -378 | U18: -288 | Y18: -1850
A19: Braptech | E19: -88.98 | I19: -88.98 | L19: -90 | N19: -90 | U19: -90 | Y19: -447.96
A20: Caique Oliveira | S20: 0 | Y20: 0
A21: Cartão de Credito | F21: -1104.39 | G21: -779.83 | J21: -3106.48 | Q21: -4688.05 | V21: -2127.27 | Y21: -11806.02
A22: clicksign | G22: -68 | J22: -59.5 | M22: -90 | T22: -39 | Y22: -256.5
A23: Comissão Jordao | L23: -400 | Y23: -400
A24: Comissão Rosh | L24: -500 | Y24: -500
A25: Contador | D25: -240 | Y25: -240
A26: Contador Orla Digital | I26: -450 | L26: -450 | N26: -450 | U26: -450 | Y26: -1800
A27: Contador Orla Tech | I27: -450 | L27: -450 | N27: -450 | U27: -450 | Y27: -1800
A28: Erickson Adiantamento | S28: -1500 | Y28: -1500
A29: Ericsson Teixeira | S29: 0 | Y29: 0
A30: Fernando | S30: -1200 | Y30: -1200
A31: Fernando Jorge | M31: -343 | Y31: -343
A32: Gabi reembolso | U32: -960.63 | Y32: -960.63
A33: Gabriel Paiva | S33: -9000 | Y33: -9000
A34: Gabriela Briglia Coni | S34: -6500 | Y34: -6500
A35: Gabriela Coni | M35: -6500 | Y35: -6500
A36: Gustavo | J36: -9500 | Y36: -9500
A37: Gustavo - adiantamento | H37: -1500 | Y37: -1500
A38: Gustavo Celular | L38: -400 | N38: -400 | U38: -400 | Y38: -1200
A39: Gustavo Rodrigues | M39: -9500 | S39: -9500 | Y39: -19000
A40: Imposto Orla Digital | C40: -649.2 | I40: -428.4 | L40: -208.8 | N40: 10375.68 | U40: -30281.21 | Y40: -21191.93
A41: Imposto Orla Tech | I41: -2386.56 | L41: -2976.384 | N41: -8551.73 | U41: -7905.97 | Y41: -21820.644
A42: Inss Kaique | C42: -148.5 | I42: -148.5 | L42: -148.5 | N42: -148.5 | U42: -150 | Y42: -744
A43: Inss Moha | I43: -148.5 | L43: -148.5 | N43: -148.5 | U43: -150 | Y43: -595.5
A44: Inss Saba | I44: -148.5 | L44: -148.5 | N44: -148.5 | U44: -150 | Y44: -595.5
A45: Irmã aleph | X45: -3750 | Y45: -3750
A46: Jonatham Gomes | S46: -2857.1429 | Y46: -2857.1429
A47: Jose Neto | S47: -18000 | Y47: -18000
A48: Manutenção ar | R48: -157.5 | U48: 0 | Y48: -157.5
A49: Mateus Chaves | M49: -4429 | S49: -10000 | Y49: -14429
A50: Matheus - adiantamento | H50: -1600 | Y50: -1600
A51: Matheus Alcatrao | T51: -5714.2857 | Y51: -5714.2857
A52: Matheus Cepil | J52: -9500 | M52: -9500 | Y52: -19000
A53: Nathan Reembolso PI | U53: -739.79 | Y53: -739.79
A54: Nathan Santos | N54: -15000 | S54: -15000 | Y54: -30000
A55: Neide | R55: -300 | U55: -600 | Y55: -900
A56: Neto | J56: -18000 | M56: -18000 | Y56: -36000
A57: Paiva | J57: -9000 | M57: -9000 | Y57: -18000
A58: Plano de saude | U58: -4120.76 | Y58: -4120.76
A59: Prolabore Kaique | D59: -10000 | N59: -17063.26 | U59: -16000 | Y59: -43063.26
A60: Prolabore Moha | N60: -15117.26 | U60: -16000 | Y60: -31117.26
A61: Prolabore Saba | N61: -16027.76 | U61: -14747.23 | Y61: -30774.99
A62: Rafael Panhoca | B62: -1200 | G62: -1200 | J62: -1200 | M62: -1200 | S62: -1200 | Y62: -6000
A63: Raphaela | B63: -3000 | G63: -3000 | J63: -3000 | M63: -5000 | Y63: -14000
A64: Raphaela Oliveira | S64: -5000 | Y64: -5000
A65: Reembolso Amanda | M65: -206.33 | Y65: -206.33
A66: Reembolso Caique Dev | U66: -72.22 | Y66: -72.22
A67: Reembolso Gabi
A68: Reembolso Kaique | D68: 0 | I68: -785.99 | L68: -422 | N68: -1537.23 | W68: -3183 | Y68: -5928.22
A69: Reembolso Mohamad | D69: -2668.23 | I69: -5227.31 | L69: -8905.48 | N69: -10997.22 | W69: -13868.78 | Y69: -41667.02
A70: Reembolso Note Nathan | U70: -1000 | Y70: -1000
A71: Reembolso Re | U71: -48.8 | Y71: -48.8
A72: Reembolso Saba | D72: -594 | I72: -1163.64 | L72: -5393 | N72: -9777.28 | W72: -9345.05 | Y72: -26272.97
A73: Renata Dias | S73: 0 | Y73: 0
A74: TFE Orla Digital | N74: -206.68 | Y74: -206.68
A75: TFE Orla Tech | N75: -236.98 | Y75: -236.98
A76: (vazio)
A77: Total Geral | B77: -14420 | C77: -797.7 | D77: -13502.23 | E77: -88.98 | F77: -1104.39 | G77: -16083.83 | H77: -3100 | I77: -11426.38 | J77: -79365.98 | K77: -1565 | L77: -20641.164 | M77: -89768.33 | N77: -89233.22 | O77: -1700 | Q77: -4688.05 | R77: -457.5 | S77: -128178.58 | T77: -5753.2857 | U77: -99704.61 | V77: -2127.27 | W77: -26396.83 | X77: -3750 | Y77: -613853.33
X78: =X77/16 -> -234.375 | Y78: =Y77/16 -> -38365.833 | Z78: 93.75
Z81: 80
Z82: =Z81*3 -> 240
Z83: =Z82*4 -> 960

Sheet PAGAMENTOS
B4: Pessoas | C4: Valor | D4: Data de pagamento | E4: Mês de competencia | F4: Tipo
B5: Allan | C5: -10000 | D5: 44990 | E5: 44958 | F5: Nota
B6: Raphaela | C6: -3000 | D6: 44990 | E6: 44958 | F6: Nota
B7: Rafael Panhoca | C7: -1200 | D7: 44990 | E7: 44958 | F7: Transferencia
B8: Arthur | C8: -220 | D8: 44990 | E8: 44958 | F8: Nota
B9: Imposto Orla Digital | C9: -649.2 | D9: 45005 | E9: 44958 | F9: Boleto
B10: Inss Kaique | C10: -148.5 | D10: 45005 | E10: 44958 | F10: Boleto
B11: Contador | C11: -240 | D11: 44998 | E11: 44958 | F11: Boleto
B12: Braptech | C12: -88.98 | D12: 45000 | E12: 44958 | F12: Boleto
B13: Cartão de Credito | C13: -1104.39 | D13: 44993 | E13: 44958 | F13: Boleto
B14: Reembolso Kaique | C14: =[2]REEMBOLSOS!E33 -> 0 | D14: 44998 | E14: 44958 | F14: Reembolso
B15: Reembolso Mohamad | C15: =+[2]REEMBOLSOS!E35+[2]REEMBOLSOS!E18 -> -2668.23 | D15: 44998 | E15: 44958 | F15: Reembolso
B16: Reembolso Saba | C16: =[2]REEMBOLSOS!E3+[2]REEMBOLSOS!E30 -> -594 | D16: 44998 | E16: 44958 | F16: Reembolso
B17: Prolabore Kaique | C17: -10000 | D17: 44998 | E17: 44958 | F17: Pro-labore
B18: Allan | C18: -10000 | D18: 45021 | E18: 44986 | F18: Nota
B19: Raphaela | C19: -3000 | D19: 45021 | E19: 44986 | F19: Nota
B20: Rafael Panhoca | C20: -1200 | D20: 45021 | E20: 44986 | F20: Transferencia
B21: Arthur | C21: -1036 | D21: 45021 | E21: 44986 | F21: Nota
B22: Matheus - adiantamento | C22: -1600 | D22: 45017 | E22: 44986
B23: Gustavo - adiantamento | C23: -1500 | D23: 45017 | E23: 44986
B24: Imposto Orla Digital | C24: =[2]PAGAMENTOS!F4 -> -428.4 | D24: 45036 | E24: 44986 | F24: Boleto
B25: Imposto Orla Tech | C25: =[2]PAGAMENTOS!F5 -> -2386.56 | D25: 45036 | E25: 44986
B26: Inss Kaique | C26: -148.5 | D26: 45036 | E26: 44986 | F26: Boleto
B27: Inss Saba | C27: -148.5 | D27: 45036 | E27: 44986
B28: Inss Moha | C28: -148.5 | D28: 45036 | E28: 44986
B29: Contador Orla Tech | C29: -450 | D29: 45036 | E29: 44986 | F29: Boleto
B30: Contador Orla Digital | C30: -450 | D30: 45036 | E30: 44986
B31: Braptech | C31: -88.98 | D31: 45036 | E31: 44986 | F31: Boleto
B32: clicksign | C32: -68 | D32: 45021 | E32: 44986
B33: Cartão de Credito | C33: -779.83 | D33: 45021 | E33: 44986 | F33: Boleto
B34: Reembolso Kaique | C34: =[2]REEMBOLSOS!F14+[2]REEMBOLSOS!F33 -> -785.99 | D34: 45036 | E34: 44986 | F34: Reembolso
B35: Reembolso Mohamad | C35: =[2]REEMBOLSOS!F35+[2]REEMBOLSOS!F18 -> -5227.31 | D35: 45036 | E35: 44986 | F35: Reembolso
B36: Reembolso Saba | C36: =[2]REEMBOLSOS!F3+[2]REEMBOLSOS!F30 -> -1163.64 | D36: 45036 | E36: 44986 | F36: Reembolso
B37: Allan | C37: -10000 | D37: 45051 | E37: 45017
B38: Raphaela | C38: -3000 | D38: 45051 | E38: 45017
B39: Amanda | C39: -3000 | D39: 45051 | E39: 45017
B40: Rafael Panhoca | C40: -1200 | D40: 45051 | E40: 45017
B41: Arthur | C41: -13000 | D41: 45051 | E41: 45017
B42: Arthur Freela | C42: -1184 | D42: 45068 | E42: 45017 | F42: =C42/16 -> -74
B43: Neto | C43: -18000 | D43: 45051 | E43: 45017
B44: Paiva | C44: -9000 | D44: 45051 | E44: 45017
B45: Matheus Cepil | C45: -9500 | D45: 45051 | E45: 45017
B46: Gustavo | C46: -9500 | D46: 45051 | E46: 45017
B47: Adiantamento Mateus 2 | C47: -381 | D47: 45068 | E47: 45017
B48: Gustavo Celular | C48: -400 | D48: 45065 | E48: 45017
B49: Comissão Jordao | C49: -400 | D49: 45065 | E49: 45017
B50: Comissão Rosh | C50: -500 | D50: 45065 | E50: 45017
B51: Imposto Orla Digital | C51: ='DRE ORLA 2023'!D13 -> -208.8 | D51: 45065 | E51: 45017
B52: Imposto Orla Tech | C52: ='DRE ORLA 2023'!F12-'DRE ORLA 2023'!D13 -> -2976.384 | D52: 45065 | E52: 45017
B53: Inss Kaique | C53: -148.5 | D53: 45065 | E53: 45017
B54: Inss Saba | C54: -148.5 | D54: 45065 | E54: 45017
B55: Inss Moha | C55: -148.5 | D55: 45065 | E55: 45017
B56: Contador Orla Tech | C56: -450 | D56: 45065 | E56: 45017
B57: Contador Orla Digital | C57: -450 | D57: 45065 | E57: 45017
B58: Braptech | C58: ='DRE ORLA 2023'!E65 -> -90 | D58: 45065 | E58: 45017
B59: clicksign | C59: ='DRE ORLA 2023'!F48 -> -59.5 | D59: 45051 | E59: 45017
B60: Cartão de Credito | C60: -3106.48 | D60: 45051 | E60: 45017
B61: Aleph | C61: =-LPs!C32 -> 0 | D61: 45065 | E61: 45017
B62: Reembolso Kaique | C62: ='DRE ORLA 2023'!F68 -> -422 | D62: 45065 | E62: 45017
B63: Reembolso Mohamad | C63: ='DRE ORLA 2023'!F69 -> -8905.48 | D63: 45065 | E63: 45017
B64: Reembolso Saba | C64: ='DRE ORLA 2023'!F70 -> -5393 | D64: 45065 | E64: 45017
B65: Allan | C65: -10000 | D65: 45082 | E65: 45047
B66: Allan freela | C66: =-13*60 -> -780 | D66: 45097 | E66: 45047
B67: Raphaela | C67: -5000 | D67: 45082 | E67: 45047
B68: Amanda | C68: -3000 | D68: 45082 | E68: 45047
B69: Rafael Panhoca | C69: -1200 | D69: 45082 | E69: 45047
B70: Arthur | C70: -13000 | D70: 45082 | E70: 45047
B71: Arthur Freela | C71: -378 | D71: 45097 | E71: 45047
B72: Neto | C72: -18000 | D72: 45082 | E72: 45047
B73: Paiva | C73: -9000 | D73: 45082 | E73: 45047
B74: Matheus Cepil | C74: -9500 | D74: 45082 | E74: 45047
B75: Gustavo Rodrigues | C75: -9500 | D75: 45082 | E75: 45047
B76: Gabriela Coni | C76: -6500 | D76: 45082 | E76: 45047
B77: Mateus Chaves | C77: =-3429-1000 -> -4429 | D77: 45082 | E77: 45047
B78: Fernando Jorge | C78: -343 | D78: 45082 | E78: 45047
B79: Nathan Santos | C79: -15000 | D79: 45097 | E79: 45047
B80: Gustavo Celular | C80: -400 | D80: 45097 | E80: 45047
B81: Imposto Orla Digital | C81: 10375.68 | D81: 45097 | E81: 45047
B82: Imposto Orla Tech | C82: -8551.73 | D82: 45097 | E82: 45047
B83: TFE Orla Digital | C83: -206.68 | D83: 45097 | E83: 45047
B84: TFE Orla Tech | C84: -236.98 | D84: 45097 | E84: 45047
B85: Inss Kaique | C85: -148.5 | D85: 45097 | E85: 45047
B86: Inss Saba | C86: -148.5 | D86: 45097 | E86: 45047
B87: Inss Moha | C87: -148.5 | D87: 45097 | E87: 45047
B88: Contador Orla Tech | C88: -450 | D88: 45097 | E88: 45047
B89: Contador Orla Digital | C89: -450 | D89: 45097 | E89: 45047
B90: Braptech | C90: -90 | D90: 45097 | E90: 45047
B91: clicksign | C91: =-51-39 -> -90 | D91: 45082 | E91: 45047
B92: Cartão de Credito | C92: -4688.05 | D92: 45085 | E92: 45047
B93: Reembolso Kaique | C93: =REEMBOLSO!G23 -> -1537.23 | D93: 45097 | E93: 45047
B94: Reembolso Mohamad | C94: =REEMBOLSO!G61+REEMBOLSO!G34 -> -10997.22 | D94: 45097 | E94: 45047
B95: Reembolso Saba | C95: =REEMBOLSO!G3+REEMBOLSO!G52 -> -9777.28 | D95: 45097 | E95: 45047
B96: Reembolso Amanda | C96: =-85.09-13.92-13.47-93.85 -> -206.33 | D96: 45082 | E96: 45047
B97: Alteração da empresa | C97: -1700 | D97: 45078 | E97: 45047
B98: Prolabore Kaique | C98: ='DRE ORLA 2023'!G73-'DRE ORLA 2023'!G87-'DRE ORLA 2023'!G88 -> -17063.26 | D98: 45097 | E98: 45047
B99: Prolabore Moha | C99: ='DRE ORLA 2023'!G74 -> -15117.26 | D99: 45097 | E99: 45047
B100: Prolabore Saba | C100: ='DRE ORLA 2023'!G75-'DRE ORLA 2023'!G89 -> -16027.76 | D100: 45097 | E100: 45047
B101: Advogado | C101: -2100 | D101: 45097 | E101: 45047
B102: Manutenção ar | C102: -157.5 | D102: 45098 | E102: 45047
B103: Neide | C103: -300 | D103: 45098 | E103: 45047
...

Sheet VENDAS
B4: Cliente | C4: Projeto | D4: Valor | E4: Mês | H4: Sum of Valor | I4: Column Labels
B5: Cuponi | C5: App | D5: 10820 | E5: 44927 | I5: Jan | J5: Feb | K5: Mar | L5: Apr | M5: Grand Total
B6: Cuponi | C6: App | D6: 7140 | E6: 44958 | H6: Row Labels
B7: Cuponi | C7: App | D7: 3480 | E7: 44986 | H7: Anbima | L7: 605808 | M7: 605808
B8: Anbima | C8: Reune | D8: 605808 | E8: 45017 | H8: Reune | L8: 605808 | M8: 605808
B9: Crefisa | C9: Crefisa+ | D9: 469324.8 | E9: 45017 | H9: Crefisa | L9: 469324.8 | M9: 469324.8
B10: Manipulae | C10: Produto & Design | D10: 210480 | E10: 44958 | H10: Crefisa+ | L10: 469324.8 | M10: 469324.8
B11: Manipulae | C11: Desenvolvedores React | D11: 77414.4 | E11: 44986 | H11: Cuponi | I11: 10820 | J11: 7140 | K11: 3480 | M11: 21440
B12: Manipulae | C12: Lps Mani | D12: 11872 | E12: 45017 | H12: App | I12: 10820 | J12: 7140 | K12: 3480 | M12: 21440
B13: Geonoma | C13: Institucional | D13: 14000 | E13: 45017 | H13: Geonoma | L13: 14000 | M13: 14000
B14: Warren | C14: Institucional | D14: 10000 | E14: 45017 | H14: Institucional | L14: 14000 | M14: 14000
B15: Vip Financeira | C15: Performance | D15: 20000 | E15: 45017 | H15: Manipulae | J15: 210480 | K15: 77414.4 | L15: 11872 | M15: 299766.4
H16: Desenvolvedores React | K16: 77414.4 | M16: 77414.4
H17: Lps Mani | L17: 11872 | M17: 11872
H18: Produto & Design | J18: 210480 | M18: 210480
H19: Vip Financeira | L19: 20000 | M19: 20000
H20: Performance | L20: 20000 | M20: 20000
H21: Warren | L21: 10000 | M21: 10000
H22: Institucional | L22: 10000 | M22: 10000
H23: Grand Total | I23: 10820 | J23: 217620 | K23: 80894.4 | L23: 1131004.8 | M23: 1440339.2
H27: Clientes | I27: Percentual
H28: Cuponi | I28: =GETPIVOTDATA("Valor",$H$4,"Cliente","Cuponi")/GETPIVOTDATA("Valor",$H$4) -> 0.014885383 | K28: 280 | L28: 168 | M28: =K28*L28 -> 47040
H29: Anbima | I29: =GETPIVOTDATA("Valor",$H$4,"Cliente","Anbima")/GETPIVOTDATA("Valor",$H$4) -> 0.42060093 | K29: 350 | L29: 84 | M29: =K29*L29 -> 29400
H30: Crefisa | I30: =GETPIVOTDATA("Valor",$H$4,"Cliente","Crefisa")/GETPIVOTDATA("Valor",$H$4) -> 0.32584325
H31: Manipulae | I31: =GETPIVOTDATA("Valor",$H$4,"Cliente","Manipulae")/GETPIVOTDATA("Valor",$H$4) -> 0.20812209 | M31: =SUM(M28:M29) -> 76440
H32: Lps | I32: =(GETPIVOTDATA("Valor",$H$4,"Cliente","Warren")+GETPIVOTDATA("Valor",$H$4,"Cliente","Vip Financeira")+GETPIVOTDATA("Valor",$H$4,"Cliente","Geonoma"))/GETPIVOTDATA("Valor",$H$4) -> 0.03054836 | M32: =M31*5 -> 382200
M33: =M31/SUM(L28:L29) -> 303.33333
